[{"districtid":"001","name":"Ba \u0110\u00ecnh","type":"Qu\u1eadn","location":"21 02 08N, 105 49 38E","provinceid":"01"}, {"districtid":"002","name":"Ho\u00e0n Ki\u1ebfm","type":"Qu\u1eadn","location":"21 01 53N, 105 51 09E","provinceid":"01"}, {"districtid":"003","name":"T\u00e2y H\u1ed3","type":"Qu\u1eadn","location":"21 04 10N, 105 49 07E","provinceid":"01"}, {"districtid":"004","name":"Long Bi\u00ean","type":"Qu\u1eadn","location":"21 02 21N, 105 53 07E","provinceid":"01"}, {"districtid":"005","name":"C\u1ea7u Gi\u1ea5y","type":"Qu\u1eadn","location":"21 01 52N, 105 47 20E","provinceid":"01"}, {"districtid":"006","name":"\u0110\u1ed1ng \u0110a","type":"Qu\u1eadn","location":"21 00 56N, 105 49 06E","provinceid":"01"}, {"districtid":"007","name":"Hai B\u00e0 Tr\u01b0ng","type":"Qu\u1eadn","location":"21 00 27N, 105 51 35E","provinceid":"01"}, {"districtid":"008","name":"Ho\u00e0ng Mai","type":"Qu\u1eadn","location":"20 58 33N, 105 51 22E","provinceid":"01"}, {"districtid":"009","name":"Thanh Xu\u00e2n","type":"Qu\u1eadn","location":"20 59 44N, 105 48 56E","provinceid":"01"}, {"districtid":"016","name":"S\u00f3c S\u01a1n","type":"Huy\u1ec7n","location":"21 16 55N, 105 49 46E","provinceid":"01"}, {"districtid":"017","name":"\u0110\u00f4ng Anh","type":"Huy\u1ec7n","location":"21 08 16N, 105 49 38E","provinceid":"01"}, {"districtid":"018","name":"Gia L\u00e2m","type":"Huy\u1ec7n","location":"21 01 28N, 105 56 54E","provinceid":"01"}, {"districtid":"019","name":"T\u1eeb Li\u00eam","type":"Huy\u1ec7n","location":"21 02 39N, 105 45 32E","provinceid":"01"}, {"districtid":"020","name":"Thanh Tr\u00ec","type":"Huy\u1ec7n","location":"20 56 32N, 105 50 55E","provinceid":"01"}, {"districtid":"024","name":"H\u00e0 Giang","type":"Th\u1ecb X\u00e3","location":"22 46 23N, 105 02 39E","provinceid":"02"}, {"districtid":"026","name":"\u0110\u1ed3ng V\u0103n","type":"Huy\u1ec7n","location":"23 14 34N, 105 15 48E","provinceid":"02"}, {"districtid":"027","name":"M\u00e8o V\u1ea1c","type":"Huy\u1ec7n","location":"23 09 10N, 105 26 38E","provinceid":"02"}, {"districtid":"028","name":"Y\u00ean Minh","type":"Huy\u1ec7n","location":"23 04 20N, 105 10 13E","provinceid":"02"}, {"districtid":"029","name":"Qu\u1ea3n B\u1ea1","type":"Huy\u1ec7n","location":"23 04 03N, 104 58 05E","provinceid":"02"}, {"districtid":"030","name":"V\u1ecb Xuy\u00ean","type":"Huy\u1ec7n","location":"22 45 50N, 104 56 26E","provinceid":"02"}, {"districtid":"031","name":"B\u1eafc M\u00ea","type":"Huy\u1ec7n","location":"22 45 48N, 105 16 26E","provinceid":"02"}, {"districtid":"032","name":"Ho\u00e0ng Su Ph\u00ec","type":"Huy\u1ec7n","location":"22 41 37N, 104 40 06E","provinceid":"02"}, {"districtid":"033","name":"X\u00edn M\u1ea7n","type":"Huy\u1ec7n","location":"22 38 05N, 104 28 35E","provinceid":"02"}, {"districtid":"034","name":"B\u1eafc Quang","type":"Huy\u1ec7n","location":"22 23 42N, 104 55 06E","provinceid":"02"}, {"districtid":"035","name":"Quang B\u00ecnh","type":"Huy\u1ec7n","location":"22 23 07N, 104 37 11E","provinceid":"02"}, {"districtid":"040","name":"Cao B\u1eb1ng","type":"Th\u1ecb X\u00e3","location":"22 39 20N, 106 15 20E","provinceid":"04"}, {"districtid":"042","name":"B\u1ea3o L\u00e2m","type":"Huy\u1ec7n","location":"22 52 37N, 105 27 28E","provinceid":"04"}, {"districtid":"043","name":"B\u1ea3o L\u1ea1c","type":"Huy\u1ec7n","location":"22 52 31N, 105 42 41E","provinceid":"04"}, {"districtid":"044","name":"Th\u00f4ng N\u00f4ng","type":"Huy\u1ec7n","location":"22 49 09N, 105 57 05E","provinceid":"04"}, {"districtid":"045","name":"H\u00e0 Qu\u1ea3ng","type":"Huy\u1ec7n","location":"22 53 42N, 106 06 32E","provinceid":"04"}, {"districtid":"046","name":"Tr\u00e0 L\u0129nh","type":"Huy\u1ec7n","location":"22 48 14N, 106 19 47E","provinceid":"04"}, {"districtid":"047","name":"Tr\u00f9ng Kh\u00e1nh","type":"Huy\u1ec7n","location":"22 49 31N, 106 33 58E","provinceid":"04"}, {"districtid":"048","name":"H\u1ea1 Lang","type":"Huy\u1ec7n","location":"22 42 37N, 106 41 42E","provinceid":"04"}, {"districtid":"049","name":"Qu\u1ea3ng Uy\u00ean","type":"Huy\u1ec7n","location":"22 40 15N, 106 27 42E","provinceid":"04"}, {"districtid":"050","name":"Ph\u1ee5c Ho\u00e0","type":"Huy\u1ec7n","location":"22 33 52N, 106 30 02E","provinceid":"04"}, {"districtid":"051","name":"Ho\u00e0 An","type":"Huy\u1ec7n","location":"22 41 20N, 106 02 05E","provinceid":"04"}, {"districtid":"052","name":"Nguy\u00ean B\u00ecnh","type":"Huy\u1ec7n","location":"22 38 52N, 105 57 02E","provinceid":"04"}, {"districtid":"053","name":"Th\u1ea1ch An","type":"Huy\u1ec7n","location":"22 28 51N, 106 19 51E","provinceid":"04"}, {"districtid":"058","name":"B\u1eafc K\u1ea1n","type":"Th\u1ecb X\u00e3","location":"22 08 00N, 105 51 10E","provinceid":"06"}, {"districtid":"060","name":"P\u00e1c N\u1eb7m","type":"Huy\u1ec7n","location":"22 35 46N, 105 40 25E","provinceid":"06"}, {"districtid":"061","name":"Ba B\u1ec3","type":"Huy\u1ec7n","location":"22 23 54N, 105 43 30E","provinceid":"06"}, {"districtid":"062","name":"Ng\u00e2n S\u01a1n","type":"Huy\u1ec7n","location":"22 25 50N, 106 01 00E","provinceid":"06"}, {"districtid":"063","name":"B\u1ea1ch Th\u00f4ng","type":"Huy\u1ec7n","location":"22 12 04N, 105 51 01E","provinceid":"06"}, {"districtid":"064","name":"Ch\u1ee3 \u0110\u1ed3n","type":"Huy\u1ec7n","location":"22 11 18N, 105 34 43E","provinceid":"06"}, {"districtid":"065","name":"Ch\u1ee3 M\u1edbi","type":"Huy\u1ec7n","location":"21 57 56N, 105 51 29E","provinceid":"06"}, {"districtid":"066","name":"Na R\u00ec","type":"Huy\u1ec7n","location":"22 09 48N, 106 05 09E","provinceid":"06"}, {"districtid":"070","name":"Tuy\u00ean Quang","type":"Th\u1ecb X\u00e3","location":"21 49 40N, 105 13 12E","provinceid":"08"}, {"districtid":"072","name":"N\u00e0 Hang","type":"Huy\u1ec7n","location":"22 28 34N, 105 21 03E","provinceid":"08"}, {"districtid":"073","name":"Chi\u00eam H\u00f3a","type":"Huy\u1ec7n","location":"22 12 49N, 105 14 32E","provinceid":"08"}, {"districtid":"074","name":"H\u00e0m Y\u00ean","type":"Huy\u1ec7n","location":"22 05 46N, 105 00 13E","provinceid":"08"}, {"districtid":"075","name":"Y\u00ean S\u01a1n","type":"Huy\u1ec7n","location":"21 51 53N, 105 18 14E","provinceid":"08"}, {"districtid":"076","name":"S\u01a1n D\u01b0\u01a1ng","type":"Huy\u1ec7n","location":"21 40 22N, 105 22 57E","provinceid":"08"}, {"districtid":"080","name":"L\u00e0o Cai","type":"Th\u00e0nh Ph\u1ed1","location":"22 25 07N, 103 58 43E","provinceid":"10"}, {"districtid":"082","name":"B\u00e1t X\u00e1t","type":"Huy\u1ec7n","location":"22 35 50N, 103 44 49E","provinceid":"10"}, {"districtid":"083","name":"M\u01b0\u1eddng Kh\u01b0\u01a1ng","type":"Huy\u1ec7n","location":"22 41 05N, 104 08 26E","provinceid":"10"}, {"districtid":"084","name":"Si Ma Cai","type":"Huy\u1ec7n","location":"22 39 46N, 104 16 05E","provinceid":"10"}, {"districtid":"085","name":"B\u1eafc H\u00e0","type":"Huy\u1ec7n","location":"22 30 08N, 104 18 54E","provinceid":"10"}, {"districtid":"086","name":"B\u1ea3o Th\u1eafng","type":"Huy\u1ec7n","location":"22 22 47N, 104 10 00E","provinceid":"10"}, {"districtid":"087","name":"B\u1ea3o Y\u00ean","type":"Huy\u1ec7n","location":"22 17 38N, 104 25 02E","provinceid":"10"}, {"districtid":"088","name":"Sa Pa","type":"Huy\u1ec7n","location":"22 18 54N, 103 54 18E","provinceid":"10"}, {"districtid":"089","name":"V\u0103n B\u00e0n","type":"Huy\u1ec7n","location":"22 03 48N, 104 10 59E","provinceid":"10"}, {"districtid":"094","name":"\u0110i\u1ec7n Bi\u00ean Ph\u1ee7","type":"Th\u00e0nh Ph\u1ed1","location":"21 24 52N, 103 02 31E","provinceid":"11"}, {"districtid":"095","name":"M\u01b0\u1eddng Lay","type":"Th\u1ecb X\u00e3","location":"22 01 47N, 103 07 10E","provinceid":"11"}, {"districtid":"096","name":"M\u01b0\u1eddng Nh\u00e9","type":"Huy\u1ec7n","location":"22 06 11N, 102 30 54E","provinceid":"11"}, {"districtid":"097","name":"M\u01b0\u1eddng Ch\u00e0","type":"Huy\u1ec7n","location":"21 50 31N, 103 03 15E","provinceid":"11"}, {"districtid":"098","name":"T\u1ee7a Ch\u00f9a","type":"Huy\u1ec7n","location":"21 58 19N, 103 23 01E","provinceid":"11"}, {"districtid":"099","name":"Tu\u1ea7n Gi\u00e1o","type":"Huy\u1ec7n","location":"21 38 03N, 103 21 06E","provinceid":"11"}, {"districtid":"100","name":"\u0110i\u1ec7n Bi\u00ean","type":"Huy\u1ec7n","location":"21 15 19N, 103 03 19E","provinceid":"11"}, {"districtid":"101","name":"\u0110i\u1ec7n Bi\u00ean \u0110\u00f4ng","type":"Huy\u1ec7n","location":"21 14 07N, 103 15 19E","provinceid":"11"}, {"districtid":"102","name":"M\u01b0\u1eddng \u1ea2ng","type":"Huy\u1ec7n","location":"","provinceid":"11"}, {"districtid":"104","name":"Lai Ch\u00e2u","type":"Th\u1ecb X\u00e3","location":"22 23 15N, 103 24 22E","provinceid":"12"}, {"districtid":"106","name":"Tam \u0110\u01b0\u1eddng","type":"Huy\u1ec7n","location":"22 20 16N, 103 32 53E","provinceid":"12"}, {"districtid":"107","name":"M\u01b0\u1eddng T\u00e8","type":"Huy\u1ec7n","location":"22 24 16N, 102 43 11E","provinceid":"12"}, {"districtid":"108","name":"S\u00ecn H\u1ed3","type":"Huy\u1ec7n","location":"22 17 21N, 103 18 12E","provinceid":"12"}, {"districtid":"109","name":"Phong Th\u1ed5","type":"Huy\u1ec7n","location":"22 38 24N, 103 22 38E","provinceid":"12"}, {"districtid":"110","name":"Than Uy\u00ean","type":"Huy\u1ec7n","location":"21 59 35N, 103 45 30E","provinceid":"12"}, {"districtid":"111","name":"T\u00e2n Uy\u00ean","type":"Huy\u1ec7n","location":"","provinceid":"12"}, {"districtid":"116","name":"S\u01a1n La","type":"Th\u00e0nh Ph\u1ed1","location":"21 20 39N, 103 54 52E","provinceid":"14"}, {"districtid":"118","name":"Qu\u1ef3nh Nhai","type":"Huy\u1ec7n","location":"21 46 34N, 103 39 02E","provinceid":"14"}, {"districtid":"119","name":"Thu\u1eadn Ch\u00e2u","type":"Huy\u1ec7n","location":"21 24 54N, 103 39 46E","provinceid":"14"}, {"districtid":"120","name":"M\u01b0\u1eddng La","type":"Huy\u1ec7n","location":"21 31 38N, 104 02 48E","provinceid":"14"}, {"districtid":"121","name":"B\u1eafc Y\u00ean","type":"Huy\u1ec7n","location":"21 13 23N, 104 22 09E","provinceid":"14"}, {"districtid":"122","name":"Ph\u00f9 Y\u00ean","type":"Huy\u1ec7n","location":"21 13 33N, 104 41 51E","provinceid":"14"}, {"districtid":"123","name":"M\u1ed9c Ch\u00e2u","type":"Huy\u1ec7n","location":"20 49 21N, 104 43 10E","provinceid":"14"}, {"districtid":"124","name":"Y\u00ean Ch\u00e2u","type":"Huy\u1ec7n","location":"20 59 33N, 104 19 51E","provinceid":"14"}, {"districtid":"125","name":"Mai S\u01a1n","type":"Huy\u1ec7n","location":"21 10 08N, 103 59 36E","provinceid":"14"}, {"districtid":"126","name":"S\u00f4ng M\u00e3","type":"Huy\u1ec7n","location":"21 06 04N, 103 43 56E","provinceid":"14"}, {"districtid":"127","name":"S\u1ed1p C\u1ed9p","type":"Huy\u1ec7n","location":"20 52 46N, 103 30 38E","provinceid":"14"}, {"districtid":"132","name":"Y\u00ean B\u00e1i","type":"Th\u00e0nh Ph\u1ed1","location":"21 44 28N, 104 53 42E","provinceid":"15"}, {"districtid":"133","name":"Ngh\u0129a L\u1ed9","type":"Th\u1ecb X\u00e3","location":"21 35 58N, 104 29 22E","provinceid":"15"}, {"districtid":"135","name":"L\u1ee5c Y\u00ean","type":"Huy\u1ec7n","location":"22 06 44N, 104 43 12E","provinceid":"15"}, {"districtid":"136","name":"V\u0103n Y\u00ean","type":"Huy\u1ec7n","location":"21 55 55N, 104 33 51E","provinceid":"15"}, {"districtid":"137","name":"M\u00f9 Cang Ch\u1ea3i","type":"Huy\u1ec7n","location":"21 48 22N, 104 09 01E","provinceid":"15"}, {"districtid":"138","name":"Tr\u1ea5n Y\u00ean","type":"Huy\u1ec7n","location":"21 42 20N, 104 48 56E","provinceid":"15"}, {"districtid":"139","name":"Tr\u1ea1m T\u1ea5u","type":"Huy\u1ec7n","location":"21 30 40N, 104 28 03E","provinceid":"15"}, {"districtid":"140","name":"V\u0103n Ch\u1ea5n","type":"Huy\u1ec7n","location":"21 34 15N, 104 35 19E","provinceid":"15"}, {"districtid":"141","name":"Y\u00ean B\u00ecnh","type":"Huy\u1ec7n","location":"21 52 24N, 104 55 16E","provinceid":"15"}, {"districtid":"148","name":"H\u00f2a B\u00ecnh","type":"Th\u00e0nh Ph\u1ed1","location":"20 50 36N, 105 19 20E","provinceid":"17"}, {"districtid":"150","name":"\u0110\u00e0 B\u1eafc","type":"Huy\u1ec7n","location":"20 55 58N, 105 04 52E","provinceid":"17"}, {"districtid":"151","name":"K\u1ef3 S\u01a1n","type":"Huy\u1ec7n","location":"20 54 06N, 105 23 18E","provinceid":"17"}, {"districtid":"152","name":"L\u01b0\u01a1ng S\u01a1n","type":"Huy\u1ec7n","location":"20 53 16N, 105 30 55E","provinceid":"17"}, {"districtid":"153","name":"Kim B\u00f4i","type":"Huy\u1ec7n","location":"20 40 34N, 105 32 15E","provinceid":"17"}, {"districtid":"154","name":"Cao Phong","type":"Huy\u1ec7n","location":"20 41 23N, 105 17 48E","provinceid":"17"}, {"districtid":"155","name":"T\u00e2n L\u1ea1c","type":"Huy\u1ec7n","location":"20 36 44N, 105 15 03E","provinceid":"17"}, {"districtid":"156","name":"Mai Ch\u00e2u","type":"Huy\u1ec7n","location":"20 40 56N, 104 59 46E","provinceid":"17"}, {"districtid":"157","name":"L\u1ea1c S\u01a1n","type":"Huy\u1ec7n","location":"20 29 59N, 105 24 57E","provinceid":"17"}, {"districtid":"158","name":"Y\u00ean Th\u1ee7y","type":"Huy\u1ec7n","location":"20 25 42N, 105 37 59E","provinceid":"17"}, {"districtid":"159","name":"L\u1ea1c Th\u1ee7y","type":"Huy\u1ec7n","location":"20 29 12N, 105 44 06E","provinceid":"17"}, {"districtid":"164","name":"Th\u00e1i Nguy\u00ean","type":"Th\u00e0nh Ph\u1ed1","location":"21 33 20N, 105 48 26E","provinceid":"19"}, {"districtid":"165","name":"S\u00f4ng C\u00f4ng","type":"Th\u1ecb X\u00e3","location":"21 29 14N, 105 48 47E","provinceid":"19"}, {"districtid":"167","name":"\u0110\u1ecbnh H\u00f3a","type":"Huy\u1ec7n","location":"21 53 50N, 105 38 01E","provinceid":"19"}, {"districtid":"168","name":"Ph\u00fa L\u01b0\u01a1ng","type":"Huy\u1ec7n","location":"21 45 57N, 105 43 22E","provinceid":"19"}, {"districtid":"169","name":"\u0110\u1ed3ng H\u1ef7","type":"Huy\u1ec7n","location":"21 41 10N, 105 55 43E","provinceid":"19"}, {"districtid":"170","name":"V\u00f5 Nhai","type":"Huy\u1ec7n","location":"21 47 14N, 106 02 29E","provinceid":"19"}, {"districtid":"171","name":"\u0110\u1ea1i T\u1eeb","type":"Huy\u1ec7n","location":"21 36 17N, 105 37 28E","provinceid":"19"}, {"districtid":"172","name":"Ph\u1ed5 Y\u00ean","type":"Huy\u1ec7n","location":"21 27 08N, 105 45 19E","provinceid":"19"}, {"districtid":"173","name":"Ph\u00fa B\u00ecnh","type":"Huy\u1ec7n","location":"21 29 36N, 105 57 42E","provinceid":"19"}, {"districtid":"178","name":"L\u1ea1ng S\u01a1n","type":"Th\u00e0nh Ph\u1ed1","location":"21 51 19N, 106 44 50E","provinceid":"20"}, {"districtid":"180","name":"Tr\u00e0ng \u0110\u1ecbnh","type":"Huy\u1ec7n","location":"22 18 09N, 106 26 32E","provinceid":"20"}, {"districtid":"181","name":"B\u00ecnh Gia","type":"Huy\u1ec7n","location":"22 03 56N, 106 19 01E","provinceid":"20"}, {"districtid":"182","name":"V\u0103n L\u00e3ng","type":"Huy\u1ec7n","location":"22 01 59N, 106 34 17E","provinceid":"20"}, {"districtid":"183","name":"Cao L\u1ed9c","type":"Huy\u1ec7n","location":"21 53 05N, 106 50 34E","provinceid":"20"}, {"districtid":"184","name":"V\u0103n Quan","type":"Huy\u1ec7n","location":"21 51 04N, 106 33 04E","provinceid":"20"}, {"districtid":"185","name":"B\u1eafc S\u01a1n","type":"Huy\u1ec7n","location":"21 48 57N, 106 15 28E","provinceid":"20"}, {"districtid":"186","name":"H\u1eefu L\u0169ng","type":"Huy\u1ec7n","location":"21 34 33N, 106 20 33E","provinceid":"20"}, {"districtid":"187","name":"Chi L\u0103ng","type":"Huy\u1ec7n","location":"21 40 05N, 106 37 24E","provinceid":"20"}, {"districtid":"188","name":"L\u1ed9c B\u00ecnh","type":"Huy\u1ec7n","location":"21 40 41N, 106 58 12E","provinceid":"20"}, {"districtid":"189","name":"\u0110\u00ecnh L\u1eadp","type":"Huy\u1ec7n","location":"21 32 07N, 107 07 25E","provinceid":"20"}, {"districtid":"193","name":"H\u1ea1 Long","type":"Th\u00e0nh Ph\u1ed1","location":"20 52 24N, 107 05 23E","provinceid":"22"}, {"districtid":"194","name":"M\u00f3ng C\u00e1i","type":"Th\u00e0nh Ph\u1ed1","location":"21 26 31N, 107 55 09E","provinceid":"22"}, {"districtid":"195","name":"C\u1ea9m Ph\u1ea3","type":"Th\u1ecb X\u00e3","location":"21 03 42N, 107 17 22E","provinceid":"22"}, {"districtid":"196","name":"U\u00f4ng B\u00ed","type":"Th\u1ecb X\u00e3","location":"21 04 33N, 106 45 07E","provinceid":"22"}, {"districtid":"198","name":"B\u00ecnh Li\u00eau","type":"Huy\u1ec7n","location":"21 33 07N, 107 26 24E","provinceid":"22"}, {"districtid":"199","name":"Ti\u00ean Y\u00ean","type":"Huy\u1ec7n","location":"21 22 24N, 107 22 50E","provinceid":"22"}, {"districtid":"200","name":"\u0110\u1ea7m H\u00e0","type":"Huy\u1ec7n","location":"21 21 23N, 107 34 32E","provinceid":"22"}, {"districtid":"201","name":"H\u1ea3i H\u00e0","type":"Huy\u1ec7n","location":"21 25 50N, 107 41 26E","provinceid":"22"}, {"districtid":"202","name":"Ba Ch\u1ebd","type":"Huy\u1ec7n","location":"21 15 40N, 107 09 52E","provinceid":"22"}, {"districtid":"203","name":"V\u00e2n \u0110\u1ed3n","type":"Huy\u1ec7n","location":"20 56 17N, 107 28 02E","provinceid":"22"}, {"districtid":"204","name":"Ho\u00e0nh B\u1ed3","type":"Huy\u1ec7n","location":"21 06 30N, 107 02 43E","provinceid":"22"}, {"districtid":"205","name":"\u0110\u00f4ng Tri\u1ec1u","type":"Huy\u1ec7n","location":"21 07 10N, 106 34 36E","provinceid":"22"}, {"districtid":"206","name":"Y\u00ean H\u01b0ng","type":"Huy\u1ec7n","location":"20 55 40N, 106 51 05E","provinceid":"22"}, {"districtid":"207","name":"C\u00f4 T\u00f4","type":"Huy\u1ec7n","location":"21 05 01N, 107 49 10E","provinceid":"22"}, {"districtid":"213","name":"B\u1eafc Giang","type":"Th\u00e0nh Ph\u1ed1","location":"21 17 36N, 106 11 18E","provinceid":"24"}, {"districtid":"215","name":"Y\u00ean Th\u1ebf","type":"Huy\u1ec7n","location":"21 31 29N, 106 09 27E","provinceid":"24"}, {"districtid":"216","name":"T\u00e2n Y\u00ean","type":"Huy\u1ec7n","location":"21 23 23N, 106 05 55E","provinceid":"24"}, {"districtid":"217","name":"L\u1ea1ng Giang","type":"Huy\u1ec7n","location":"21 21 58N, 106 15 21E","provinceid":"24"}, {"districtid":"218","name":"L\u1ee5c Nam","type":"Huy\u1ec7n","location":"21 18 16N, 106 29 24E","provinceid":"24"}, {"districtid":"219","name":"L\u1ee5c Ng\u1ea1n","type":"Huy\u1ec7n","location":"21 26 15N, 106 39 09E","provinceid":"24"}, {"districtid":"220","name":"S\u01a1n \u0110\u1ed9ng","type":"Huy\u1ec7n","location":"21 19 42N, 106 51 09E","provinceid":"24"}, {"districtid":"221","name":"Y\u00ean D\u0169ng","type":"Huy\u1ec7n","location":"21 12 22N, 106 14 12E","provinceid":"24"}, {"districtid":"222","name":"Vi\u1ec7t Y\u00ean","type":"Huy\u1ec7n","location":"21 16 16N, 106 04 59E","provinceid":"24"}, {"districtid":"223","name":"Hi\u1ec7p H\u00f2a","type":"Huy\u1ec7n","location":"21 15 51N, 105 57 30E","provinceid":"24"}, {"districtid":"227","name":"Vi\u1ec7t Tr\u00ec","type":"Th\u00e0nh Ph\u1ed1","location":"21 19 01N, 105 23 35E","provinceid":"25"}, {"districtid":"228","name":"Ph\u00fa Th\u1ecd","type":"Th\u1ecb X\u00e3","location":"21 24 54N, 105 13 46E","provinceid":"25"}, {"districtid":"230","name":"\u0110oan H\u00f9ng","type":"Huy\u1ec7n","location":"21 36 56N, 105 08 42E","provinceid":"25"}, {"districtid":"231","name":"H\u1ea1 Ho\u00e0","type":"Huy\u1ec7n","location":"21 35 13N, 105 00 22E","provinceid":"25"}, {"districtid":"232","name":"Thanh Ba","type":"Huy\u1ec7n","location":"21 27 04N, 105 09 10E","provinceid":"25"}, {"districtid":"233","name":"Ph\u00f9 Ninh","type":"Huy\u1ec7n","location":"21 26 59N, 105 18 13E","provinceid":"25"}, {"districtid":"234","name":"Y\u00ean L\u1eadp","type":"Huy\u1ec7n","location":"21 22 21N, 105 01 25E","provinceid":"25"}, {"districtid":"235","name":"C\u1ea9m Kh\u00ea","type":"Huy\u1ec7n","location":"21 23 04N, 105 05 25E","provinceid":"25"}, {"districtid":"236","name":"Tam N\u00f4ng","type":"Huy\u1ec7n","location":"21 18 24N, 105 14 59E","provinceid":"25"}, {"districtid":"237","name":"L\u00e2m Thao","type":"Huy\u1ec7n","location":"21 19 37N, 105 18 09E","provinceid":"25"}, {"districtid":"238","name":"Thanh S\u01a1n","type":"Huy\u1ec7n","location":"21 08 32N, 105 04 40E","provinceid":"25"}, {"districtid":"239","name":"Thanh Thu\u1ef7","type":"Huy\u1ec7n","location":"21 07 26N, 105 17 18E","provinceid":"25"}, {"districtid":"240","name":"T\u00e2n S\u01a1n","type":"Huy\u1ec7n","location":"","provinceid":"25"}, {"districtid":"243","name":"V\u0129nh Y\u00ean","type":"Th\u00e0nh Ph\u1ed1","location":"21 18 26N, 105 35 33E","provinceid":"26"}, {"districtid":"244","name":"Ph\u00fac Y\u00ean","type":"Th\u1ecb X\u00e3","location":"21 18 55N, 105 43 54E","provinceid":"26"}, {"districtid":"246","name":"L\u1eadp Th\u1ea1ch","type":"Huy\u1ec7n","location":"21 24 45N, 105 25 39E","provinceid":"26"}, {"districtid":"247","name":"Tam D\u01b0\u01a1ng","type":"Huy\u1ec7n","location":"21 21 40N, 105 33 36E","provinceid":"26"}, {"districtid":"248","name":"Tam \u0110\u1ea3o","type":"Huy\u1ec7n","location":"21 27 34N, 105 35 09E","provinceid":"26"}, {"districtid":"249","name":"B\u00ecnh Xuy\u00ean","type":"Huy\u1ec7n","location":"21 19 48N, 105 39 43E","provinceid":"26"}, {"districtid":"250","name":"M\u00ea Linh","type":"Huy\u1ec7n","location":"21 10 53N, 105 42 05E","provinceid":"01"}, {"districtid":"251","name":"Y\u00ean L\u1ea1c","type":"Huy\u1ec7n","location":"21 13 17N, 105 34 44E","provinceid":"26"}, {"districtid":"252","name":"V\u0129nh T\u01b0\u1eddng","type":"Huy\u1ec7n","location":"21 14 58N, 105 29 37E","provinceid":"26"}, {"districtid":"253","name":"S\u00f4ng L\u00f4","type":"Huy\u1ec7n","location":"","provinceid":"26"}, {"districtid":"256","name":"B\u1eafc Ninh","type":"Th\u00e0nh Ph\u1ed1","location":"21 10 48N, 106 03 58E","provinceid":"27"}, {"districtid":"258","name":"Y\u00ean Phong","type":"Huy\u1ec7n","location":"21 12 40N, 105 59 36E","provinceid":"27"}, {"districtid":"259","name":"Qu\u1ebf V\u00f5","type":"Huy\u1ec7n","location":"21 08 44N, 106 11 06E","provinceid":"27"}, {"districtid":"260","name":"Ti\u00ean Du","type":"Huy\u1ec7n","location":"21 07 37N, 106 02 19E","provinceid":"27"}, {"districtid":"261","name":"T\u1eeb S\u01a1n","type":"Th\u1ecb X\u00e3","location":"21 07 12N, 105 57 26E","provinceid":"27"}, {"districtid":"262","name":"Thu\u1eadn Th\u00e0nh","type":"Huy\u1ec7n","location":"21 02 24N, 106 04 10E","provinceid":"27"}, {"districtid":"263","name":"Gia B\u00ecnh","type":"Huy\u1ec7n","location":"21 03 55N, 106 12 53E","provinceid":"27"}, {"districtid":"264","name":"L\u01b0\u01a1ng T\u00e0i","type":"Huy\u1ec7n","location":"21 01 33N, 106 13 28E","provinceid":"27"}, {"districtid":"268","name":"H\u00e0 \u0110\u00f4ng","type":"Qu\u1eadn","location":"20 57 25N, 105 45 21E","provinceid":"01"}, {"districtid":"269","name":"S\u01a1n T\u00e2y","type":"Th\u1ecb X\u00e3","location":"21 05 51N, 105 28 27E","provinceid":"01"}, {"districtid":"271","name":"Ba V\u00ec","type":"Huy\u1ec7n","location":"21 09 40N, 105 22 43E","provinceid":"01"}, {"districtid":"272","name":"Ph\u00fac Th\u1ecd","type":"Huy\u1ec7n","location":"21 06 32N, 105 34 52E","provinceid":"01"}, {"districtid":"273","name":"\u0110an Ph\u01b0\u1ee3ng","type":"Huy\u1ec7n","location":"21 07 13N, 105 40 49E","provinceid":"01"}, {"districtid":"274","name":"Ho\u00e0i \u0110\u1ee9c","type":"Huy\u1ec7n","location":"21 01 25N, 105 42 03E","provinceid":"01"}, {"districtid":"275","name":"Qu\u1ed1c Oai","type":"Huy\u1ec7n","location":"20 58 45N, 105 36 43E","provinceid":"01"}, {"districtid":"276","name":"Th\u1ea1ch Th\u1ea5t","type":"Huy\u1ec7n","location":"21 02 17N, 105 33 05E","provinceid":"01"}, {"districtid":"277","name":"Ch\u01b0\u01a1ng M\u1ef9","type":"Huy\u1ec7n","location":"20 52 46N, 105 39 01E","provinceid":"01"}, {"districtid":"278","name":"Thanh Oai","type":"Huy\u1ec7n","location":"20 51 44N, 105 46 18E","provinceid":"01"}, {"districtid":"279","name":"Th\u01b0\u1eddng T\u00edn","type":"Huy\u1ec7n","location":"20 49 59N, 105 22 19E","provinceid":"01"}, {"districtid":"280","name":"Ph\u00fa Xuy\u00ean","type":"Huy\u1ec7n","location":"20 43 37N, 105 53 43E","provinceid":"01"}, {"districtid":"281","name":"\u1ee8ng H\u00f2a","type":"Huy\u1ec7n","location":"20 42 41N, 105 47 58E","provinceid":"01"}, {"districtid":"282","name":"M\u1ef9 \u0110\u1ee9c","type":"Huy\u1ec7n","location":"20 41 53N, 105 43 31E","provinceid":"01"}, {"districtid":"288","name":"H\u1ea3i D\u01b0\u01a1ng","type":"Th\u00e0nh Ph\u1ed1","location":"20 56 14N, 106 18 21E","provinceid":"30"}, {"districtid":"290","name":"Ch\u00ed Linh","type":"Huy\u1ec7n","location":"21 07 47N, 106 23 46E","provinceid":"30"}, {"districtid":"291","name":"Nam S\u00e1ch","type":"Huy\u1ec7n","location":"21 00 15N, 106 20 26E","provinceid":"30"}, {"districtid":"292","name":"Kinh M\u00f4n","type":"Huy\u1ec7n","location":"21 00 04N, 106 30 23E","provinceid":"30"}, {"districtid":"293","name":"Kim Th\u00e0nh","type":"Huy\u1ec7n","location":"20 55 40N, 106 30 33E","provinceid":"30"}, {"districtid":"294","name":"Thanh H\u00e0","type":"Huy\u1ec7n","location":"20 53 19N, 106 25 43E","provinceid":"30"}, {"districtid":"295","name":"C\u1ea9m Gi\u00e0ng","type":"Huy\u1ec7n","location":"20 57 05N, 106 12 29E","provinceid":"30"}, {"districtid":"296","name":"B\u00ecnh Giang","type":"Huy\u1ec7n","location":"20 52 36N, 106 11 24E","provinceid":"30"}, {"districtid":"297","name":"Gia L\u1ed9c","type":"Huy\u1ec7n","location":"20 51 01N, 106 17 34E","provinceid":"30"}, {"districtid":"298","name":"T\u1ee9 K\u1ef3","type":"Huy\u1ec7n","location":"20 49 05N, 106 24 05E","provinceid":"30"}, {"districtid":"299","name":"Ninh Giang","type":"Huy\u1ec7n","location":"20 45 13N, 106 20 09E","provinceid":"30"}, {"districtid":"300","name":"Thanh Mi\u1ec7n","type":"Huy\u1ec7n","location":"20 46 02N, 106 12 26E","provinceid":"30"}, {"districtid":"303","name":"H\u1ed3ng B\u00e0ng","type":"Qu\u1eadn","location":"20 52 37N, 106 38 32E","provinceid":"31"}, {"districtid":"304","name":"Ng\u00f4 Quy\u1ec1n","type":"Qu\u1eadn","location":"20 51 13N, 106 41 57E","provinceid":"31"}, {"districtid":"305","name":"L\u00ea Ch\u00e2n","type":"Qu\u1eadn","location":"20 50 12N, 106 40 30E","provinceid":"31"}, {"districtid":"306","name":"H\u1ea3i An","type":"Qu\u1eadn","location":"20 49 38N, 106 45 57E","provinceid":"31"}, {"districtid":"307","name":"Ki\u1ebfn An","type":"Qu\u1eadn","location":"20 48 26N, 106 38 03E","provinceid":"31"}, {"districtid":"308","name":"\u0110\u1ed3 S\u01a1n","type":"Qu\u1eadn","location":"20 42 41N, 106 44 54E","provinceid":"31"}, {"districtid":"309","name":"Kinh D\u01b0\u01a1ng","type":"Qu\u1eadn","location":"","provinceid":"31"}, {"districtid":"311","name":"Thu\u1ef7 Nguy\u00ean","type":"Huy\u1ec7n","location":"20 56 36N, 106 39 38E","provinceid":"31"}, {"districtid":"312","name":"An D\u01b0\u01a1ng","type":"Huy\u1ec7n","location":"20 53 06N, 106 35 36E","provinceid":"31"}, {"districtid":"313","name":"An L\u00e3o","type":"Huy\u1ec7n","location":"20 47 54N, 106 33 19E","provinceid":"31"}, {"districtid":"314","name":"Ki\u1ebfn Th\u1ee5y","type":"Huy\u1ec7n","location":"20 45 13N, 106 41 47E","provinceid":"31"}, {"districtid":"315","name":"Ti\u00ean L\u00e3ng","type":"Huy\u1ec7n","location":"20 42 23N, 106 36 03E","provinceid":"31"}, {"districtid":"316","name":"V\u0129nh B\u1ea3o","type":"Huy\u1ec7n","location":"20 40 56N, 106 29 57E","provinceid":"31"}, {"districtid":"317","name":"C\u00e1t H\u1ea3i","type":"Huy\u1ec7n","location":"20 47 09N, 106 58 07E","provinceid":"31"}, {"districtid":"318","name":"B\u1ea1ch Long V\u0129","type":"Huy\u1ec7n","location":"20 08 41N, 107 42 51E","provinceid":"31"}, {"districtid":"323","name":"H\u01b0ng Y\u00ean","type":"Th\u00e0nh Ph\u1ed1","location":"20 39 38N, 106 03 08E","provinceid":"33"}, {"districtid":"325","name":"V\u0103n L\u00e2m","type":"Huy\u1ec7n","location":"20 58 31N, 106 02 51E","provinceid":"33"}, {"districtid":"326","name":"V\u0103n Giang","type":"Huy\u1ec7n","location":"20 55 51N, 105 57 14E","provinceid":"33"}, {"districtid":"327","name":"Y\u00ean M\u1ef9","type":"Huy\u1ec7n","location":"20 53 45N, 106 01 21E","provinceid":"33"}, {"districtid":"328","name":"M\u1ef9 H\u00e0o","type":"Huy\u1ec7n","location":"20 55 35N, 106 05 34E","provinceid":"33"}, {"districtid":"329","name":"\u00c2n Thi","type":"Huy\u1ec7n","location":"20 48 49N, 106 05 30E","provinceid":"33"}, {"districtid":"330","name":"Kho\u00e1i Ch\u00e2u","type":"Huy\u1ec7n","location":"20 49 53N, 105 58 28E","provinceid":"33"}, {"districtid":"331","name":"Kim \u0110\u1ed9ng","type":"Huy\u1ec7n","location":"20 44 47N, 106 01 47E","provinceid":"33"}, {"districtid":"332","name":"Ti\u00ean L\u1eef","type":"Huy\u1ec7n","location":"20 40 05N, 106 07 59E","provinceid":"33"}, {"districtid":"333","name":"Ph\u00f9 C\u1eeb","type":"Huy\u1ec7n","location":"20 42 51N, 106 11 30E","provinceid":"33"}, {"districtid":"336","name":"Th\u00e1i B\u00ecnh","type":"Th\u00e0nh Ph\u1ed1","location":"20 26 45N, 106 19 56E","provinceid":"34"}, {"districtid":"338","name":"Qu\u1ef3nh Ph\u1ee5","type":"Huy\u1ec7n","location":"20 38 57N, 106 21 16E","provinceid":"34"}, {"districtid":"339","name":"H\u01b0ng H\u00e0","type":"Huy\u1ec7n","location":"20 35 38N, 106 12 42E","provinceid":"34"}, {"districtid":"340","name":"\u0110\u00f4ng H\u01b0ng","type":"Huy\u1ec7n","location":"20 32 50N, 106 20 15E","provinceid":"34"}, {"districtid":"341","name":"Th\u00e1i Th\u1ee5y","type":"Huy\u1ec7n","location":"20 32 33N, 106 32 32E","provinceid":"34"}, {"districtid":"342","name":"Ti\u1ec1n H\u1ea3i","type":"Huy\u1ec7n","location":"20 21 05N, 106 32 45E","provinceid":"34"}, {"districtid":"343","name":"Ki\u1ebfn X\u01b0\u01a1ng","type":"Huy\u1ec7n","location":"20 23 52N, 106 25 22E","provinceid":"34"}, {"districtid":"344","name":"V\u0169 Th\u01b0","type":"Huy\u1ec7n","location":"20 25 29N, 106 16 43E","provinceid":"34"}, {"districtid":"347","name":"Ph\u1ee7 L\u00fd","type":"Th\u00e0nh Ph\u1ed1","location":"20 32 19N, 105 54 55E","provinceid":"35"}, {"districtid":"349","name":"Duy Ti\u00ean","type":"Huy\u1ec7n","location":"20 37 33N, 105 58 01E","provinceid":"35"}, {"districtid":"350","name":"Kim B\u1ea3ng","type":"Huy\u1ec7n","location":"20 34 19N, 105 50 41E","provinceid":"35"}, {"districtid":"351","name":"Thanh Li\u00eam","type":"Huy\u1ec7n","location":"20 27 31N, 105 55 09E","provinceid":"35"}, {"districtid":"352","name":"B\u00ecnh L\u1ee5c","type":"Huy\u1ec7n","location":"20 29 23N, 106 02 52E","provinceid":"35"}, {"districtid":"353","name":"L\u00fd Nh\u00e2n","type":"Huy\u1ec7n","location":"20 32 55N, 106 04 48E","provinceid":"35"}, {"districtid":"356","name":"Nam \u0110\u1ecbnh","type":"Th\u00e0nh Ph\u1ed1","location":"20 25 07N, 106 09 54E","provinceid":"36"}, {"districtid":"358","name":"M\u1ef9 L\u1ed9c","type":"Huy\u1ec7n","location":"20 27 21N, 106 07 56E","provinceid":"36"}, {"districtid":"359","name":"V\u1ee5 B\u1ea3n","type":"Huy\u1ec7n","location":"20 22 57N, 106 05 35E","provinceid":"36"}, {"districtid":"360","name":"\u00dd Y\u00ean","type":"Huy\u1ec7n","location":"20 19 48N, 106 01 55E","provinceid":"36"}, {"districtid":"361","name":"Ngh\u0129a H\u01b0ng","type":"Huy\u1ec7n","location":"20 05 37N, 106 08 59E","provinceid":"36"}, {"districtid":"362","name":"Nam Tr\u1ef1c","type":"Huy\u1ec7n","location":"20 20 08N, 106 12 54E","provinceid":"36"}, {"districtid":"363","name":"Tr\u1ef1c Ninh","type":"Huy\u1ec7n","location":"20 14 42N, 106 12 45E","provinceid":"36"}, {"districtid":"364","name":"Xu\u00e2n Tr\u01b0\u1eddng","type":"Huy\u1ec7n","location":"20 17 53N, 106 21 43E","provinceid":"36"}, {"districtid":"365","name":"Giao Th\u1ee7y","type":"Huy\u1ec7n","location":"20 14 45N, 106 28 39E","provinceid":"36"}, {"districtid":"366","name":"H\u1ea3i H\u1eadu","type":"Huy\u1ec7n","location":"20 06 26N, 106 16 29E","provinceid":"36"}, {"districtid":"369","name":"Ninh B\u00ecnh","type":"Th\u00e0nh Ph\u1ed1","location":"20 14 45N, 105 58 24E","provinceid":"37"}, {"districtid":"370","name":"Tam \u0110i\u1ec7p","type":"Th\u1ecb X\u00e3","location":"20 09 42N, 103 52 43E","provinceid":"37"}, {"districtid":"372","name":"Nho Quan","type":"Huy\u1ec7n","location":"20 18 46N, 105 42 48E","provinceid":"37"}, {"districtid":"373","name":"Gia Vi\u1ec5n","type":"Huy\u1ec7n","location":"20 19 50N, 105 52 20E","provinceid":"37"}, {"districtid":"374","name":"Hoa L\u01b0","type":"Huy\u1ec7n","location":"20 15 04N, 105 55 52E","provinceid":"37"}, {"districtid":"375","name":"Y\u00ean Kh\u00e1nh","type":"Huy\u1ec7n","location":"20 11 26N, 106 04 33E","provinceid":"37"}, {"districtid":"376","name":"Kim S\u01a1n","type":"Huy\u1ec7n","location":"20 02 07N, 106 05 27E","provinceid":"37"}, {"districtid":"377","name":"Y\u00ean M\u00f4","type":"Huy\u1ec7n","location":"20 07 45N, 105 59 45E","provinceid":"37"}, {"districtid":"380","name":"Thanh H\u00f3a","type":"Th\u00e0nh Ph\u1ed1","location":"19 48 26N, 105 47 37E","provinceid":"38"}, {"districtid":"381","name":"B\u1ec9m S\u01a1n","type":"Th\u1ecb X\u00e3","location":"20 05 21N, 105 51 48E","provinceid":"38"}, {"districtid":"382","name":"S\u1ea7m S\u01a1n","type":"Th\u1ecb X\u00e3","location":"19 45 11N, 105 54 03E","provinceid":"38"}, {"districtid":"384","name":"M\u01b0\u1eddng L\u00e1t","type":"Huy\u1ec7n","location":"20 30 42N, 104 37 27E","provinceid":"38"}, {"districtid":"385","name":"Quan H\u00f3a","type":"Huy\u1ec7n","location":"20 29 15N, 104 56 35E","provinceid":"38"}, {"districtid":"386","name":"B\u00e1 Th\u01b0\u1edbc","type":"Huy\u1ec7n","location":"20 22 48N, 105 14 50E","provinceid":"38"}, {"districtid":"387","name":"Quan S\u01a1n","type":"Huy\u1ec7n","location":"20 15 17N, 104 51 58E","provinceid":"38"}, {"districtid":"388","name":"Lang Ch\u00e1nh","type":"Huy\u1ec7n","location":"20 08 58N, 105 07 40E","provinceid":"38"}, {"districtid":"389","name":"Ng\u1ecdc L\u1eb7c","type":"Huy\u1ec7n","location":"20 04 08N, 105 22 39E","provinceid":"38"}, {"districtid":"390","name":"C\u1ea9m Th\u1ee7y","type":"Huy\u1ec7n","location":"20 12 20N, 105 27 22E","provinceid":"38"}, {"districtid":"391","name":"Th\u1ea1ch Th\u00e0nh","type":"Huy\u1ec7n","location":"21 12 41N, 105 36 38E","provinceid":"38"}, {"districtid":"392","name":"H\u00e0 Trung","type":"Huy\u1ec7n","location":"20 03 20N, 105 51 20E","provinceid":"38"}, {"districtid":"393","name":"V\u0129nh L\u1ed9c","type":"Huy\u1ec7n","location":"20 02 29N, 105 39 28E","provinceid":"38"}, {"districtid":"394","name":"Y\u00ean \u0110\u1ecbnh","type":"Huy\u1ec7n","location":"20 00 31N, 105 37 44E","provinceid":"38"}, {"districtid":"395","name":"Th\u1ecd Xu\u00e2n","type":"Huy\u1ec7n","location":"19 55 39N, 105 29 14E","provinceid":"38"}, {"districtid":"396","name":"Th\u01b0\u1eddng Xu\u00e2n","type":"Huy\u1ec7n","location":"19 54 55N, 105 10 46E","provinceid":"38"}, {"districtid":"397","name":"Tri\u1ec7u S\u01a1n","type":"Huy\u1ec7n","location":"19 48 11N, 105 34 03E","provinceid":"38"}, {"districtid":"398","name":"Thi\u1ec7u Ho\u00e1","type":"Huy\u1ec7n","location":"19 53 56N, 105 40 57E","provinceid":"38"}, {"districtid":"399","name":"Ho\u1eb1ng H\u00f3a","type":"Huy\u1ec7n","location":"19 51 59N, 105 51 34E","provinceid":"38"}, {"districtid":"400","name":"H\u1eadu L\u1ed9c","type":"Huy\u1ec7n","location":"19 56 02N, 105 53 19E","provinceid":"38"}, {"districtid":"401","name":"Nga S\u01a1n","type":"Huy\u1ec7n","location":"20 00 16N, 105 59 26E","provinceid":"38"}, {"districtid":"402","name":"Nh\u01b0 Xu\u00e2n","type":"Huy\u1ec7n","location":"19 5 55N, 105 20 22E","provinceid":"38"}, {"districtid":"403","name":"Nh\u01b0 Thanh","type":"Huy\u1ec7n","location":"19 35 19N, 105 33 09E","provinceid":"38"}, {"districtid":"404","name":"N\u00f4ng C\u1ed1ng","type":"Huy\u1ec7n","location":"19 36 58N, 105 40 54E","provinceid":"38"}, {"districtid":"405","name":"\u0110\u00f4ng S\u01a1n","type":"Huy\u1ec7n","location":"19 47 44N, 105 42 19E","provinceid":"38"}, {"districtid":"406","name":"Qu\u1ea3ng X\u01b0\u01a1ng","type":"Huy\u1ec7n","location":"19 40 53N, 105 48 01E","provinceid":"38"}, {"districtid":"407","name":"T\u0129nh Gia","type":"Huy\u1ec7n","location":"19 27 13N, 105 43 38E","provinceid":"38"}, {"districtid":"412","name":"Vinh","type":"Th\u00e0nh Ph\u1ed1","location":"18 41 06N, 105 42 05E","provinceid":"40"}, {"districtid":"413","name":"C\u1eeda L\u00f2","type":"Th\u1ecb X\u00e3","location":"18 47 26N, 105 43 31E","provinceid":"40"}, {"districtid":"414","name":"Th\u00e1i Ho\u00e0","type":"Th\u1ecb X\u00e3","location":"","provinceid":"40"}, {"districtid":"415","name":"Qu\u1ebf Phong","type":"Huy\u1ec7n","location":"19 42 25N, 104 54 21E","provinceid":"40"}, {"districtid":"416","name":"Qu\u1ef3 Ch\u00e2u","type":"Huy\u1ec7n","location":"19 32 16N, 105 03 18E","provinceid":"40"}, {"districtid":"417","name":"K\u1ef3 S\u01a1n","type":"Huy\u1ec7n","location":"19 24 36N, 104 09 45E","provinceid":"40"}, {"districtid":"418","name":"T\u01b0\u01a1ng D\u01b0\u01a1ng","type":"Huy\u1ec7n","location":"19 19 15N, 104 35 41E","provinceid":"40"}, {"districtid":"419","name":"Ngh\u0129a \u0110\u00e0n","type":"Huy\u1ec7n","location":"19 21 19N, 105 26 33E","provinceid":"40"}, {"districtid":"420","name":"Qu\u1ef3 H\u1ee3p","type":"Huy\u1ec7n","location":"19 19 24N, 105 09 12E","provinceid":"40"}, {"districtid":"421","name":"Qu\u1ef3nh L\u01b0u","type":"Huy\u1ec7n","location":"19 14 01N, 105 37 00E","provinceid":"40"}, {"districtid":"422","name":"Con Cu\u00f4ng","type":"Huy\u1ec7n","location":"19 03 50N, 107 47 15E","provinceid":"40"}, {"districtid":"423","name":"T\u00e2n K\u1ef3","type":"Huy\u1ec7n","location":"19 06 11N, 105 14 14E","provinceid":"40"}, {"districtid":"424","name":"Anh S\u01a1n","type":"Huy\u1ec7n","location":"18 58 04N, 105 04 30E","provinceid":"40"}, {"districtid":"425","name":"Di\u1ec5n Ch\u00e2u","type":"Huy\u1ec7n","location":"19 01 20N, 105 34 13E","provinceid":"40"}, {"districtid":"426","name":"Y\u00ean Th\u00e0nh","type":"Huy\u1ec7n","location":"19 01 25N, 105 26 17E","provinceid":"40"}, {"districtid":"427","name":"\u0110\u00f4 L\u01b0\u01a1ng","type":"Huy\u1ec7n","location":"18 55 00N, 105 21 03E","provinceid":"40"}, {"districtid":"428","name":"Thanh Ch\u01b0\u01a1ng","type":"Huy\u1ec7n","location":"18 44 11N, 105 12 59E","provinceid":"40"}, {"districtid":"429","name":"Nghi L\u1ed9c","type":"Huy\u1ec7n","location":"18 47 41N, 105 31 30E","provinceid":"40"}, {"districtid":"430","name":"Nam \u0110\u00e0n","type":"Huy\u1ec7n","location":"18 40 28N, 105 30 32E","provinceid":"40"}, {"districtid":"431","name":"H\u01b0ng Nguy\u00ean","type":"Huy\u1ec7n","location":"18 41 13N, 105 37 41E","provinceid":"40"}, {"districtid":"436","name":"H\u00e0 T\u0129nh","type":"Th\u00e0nh Ph\u1ed1","location":"18 21 20N, 105 54 00E","provinceid":"42"}, {"districtid":"437","name":"H\u1ed3ng L\u0129nh","type":"Th\u1ecb X\u00e3","location":"18 32 05N, 105 42 40E","provinceid":"42"}, {"districtid":"439","name":"H\u01b0\u01a1ng S\u01a1n","type":"Huy\u1ec7n","location":"18 26 47N, 105 19 36E","provinceid":"42"}, {"districtid":"440","name":"\u0110\u1ee9c Th\u1ecd","type":"Huy\u1ec7n","location":"18 29 23N, 105 36 39E","provinceid":"42"}, {"districtid":"441","name":"V\u0169 Quang","type":"Huy\u1ec7n","location":"18 19 30N, 105 26 38E","provinceid":"42"}, {"districtid":"442","name":"Nghi Xu\u00e2n","type":"Huy\u1ec7n","location":"18 38 46N, 105 46 17E","provinceid":"42"}, {"districtid":"443","name":"Can L\u1ed9c","type":"Huy\u1ec7n","location":"18 26 39N, 105 46 13E","provinceid":"42"}, {"districtid":"444","name":"H\u01b0\u01a1ng Kh\u00ea","type":"Huy\u1ec7n","location":"18 11 36N, 105 41 24E","provinceid":"42"}, {"districtid":"445","name":"Th\u1ea1ch H\u00e0","type":"Huy\u1ec7n","location":"18 19 29N, 105 52 43E","provinceid":"42"}, {"districtid":"446","name":"C\u1ea9m Xuy\u00ean","type":"Huy\u1ec7n","location":"18 11 32N, 106 00 04E","provinceid":"42"}, {"districtid":"447","name":"K\u1ef3 Anh","type":"Huy\u1ec7n","location":"18 05 15N, 106 15 49E","provinceid":"42"}, {"districtid":"448","name":"L\u1ed9c H\u00e0","type":"Huy\u1ec7n","location":"","provinceid":"42"}, {"districtid":"450","name":"\u0110\u1ed3ng H\u1edbi","type":"Th\u00e0nh Ph\u1ed1","location":"17 26 53N, 106 35 15E","provinceid":"44"}, {"districtid":"452","name":"Minh H\u00f3a","type":"Huy\u1ec7n","location":"17 44 03N, 105 51 45E","provinceid":"44"}, {"districtid":"453","name":"Tuy\u00ean H\u00f3a","type":"Huy\u1ec7n","location":"17 54 04N, 105 58 17E","provinceid":"44"}, {"districtid":"454","name":"Qu\u1ea3ng Tr\u1ea1ch","type":"Huy\u1ec7n","location":"17 50 04N, 106 22 24E","provinceid":"44"}, {"districtid":"455","name":"B\u1ed1 Tr\u1ea1ch","type":"Huy\u1ec7n","location":"17 29 13N, 106 06 54E","provinceid":"44"}, {"districtid":"456","name":"Qu\u1ea3ng Ninh","type":"Huy\u1ec7n","location":"17 15 15N, 106 32 31E","provinceid":"44"}, {"districtid":"457","name":"L\u1ec7 Th\u1ee7y","type":"Huy\u1ec7n","location":"17 07 35N, 106 41 47E","provinceid":"44"}, {"districtid":"461","name":"\u0110\u00f4ng H\u00e0","type":"Th\u00e0nh Ph\u1ed1","location":"16 48 12N, 107 05 12E","provinceid":"45"}, {"districtid":"462","name":"Qu\u1ea3ng Tr\u1ecb","type":"Th\u1ecb X\u00e3","location":"16 44 37N, 107 11 20E","provinceid":"45"}, {"districtid":"464","name":"V\u0129nh Linh","type":"Huy\u1ec7n","location":"17 01 35N, 106 53 49E","provinceid":"45"}, {"districtid":"465","name":"H\u01b0\u1edbng H\u00f3a","type":"Huy\u1ec7n","location":"16 42 19N, 106 40 14E","provinceid":"45"}, {"districtid":"466","name":"Gio Linh","type":"Huy\u1ec7n","location":"16 54 49N, 106 56 16E","provinceid":"45"}, {"districtid":"467","name":"\u0110a Kr\u00f4ng","type":"Huy\u1ec7n","location":"16 33 58N, 106 55 49E","provinceid":"45"}, {"districtid":"468","name":"Cam L\u1ed9","type":"Huy\u1ec7n","location":"16 47 09N, 106 57 52E","provinceid":"45"}, {"districtid":"469","name":"Tri\u1ec7u Phong","type":"Huy\u1ec7n","location":"16 46 32N, 107 09 12E","provinceid":"45"}, {"districtid":"470","name":"H\u1ea3i L\u0103ng","type":"Huy\u1ec7n","location":"16 41 07N, 107 13 34E","provinceid":"45"}, {"districtid":"471","name":"C\u1ed3n C\u1ecf","type":"Huy\u1ec7n","location":"19 09 39N, 107 19 58E","provinceid":"45"}, {"districtid":"474","name":"Hu\u1ebf","type":"Th\u00e0nh Ph\u1ed1","location":"16 27 16N, 107 34 29E","provinceid":"46"}, {"districtid":"476","name":"Phong \u0110i\u1ec1n","type":"Huy\u1ec7n","location":"16 32 42N, 106 16 37E","provinceid":"46"}, {"districtid":"477","name":"Qu\u1ea3ng \u0110i\u1ec1n","type":"Huy\u1ec7n","location":"16 35 21N, 107 29 31E","provinceid":"46"}, {"districtid":"478","name":"Ph\u00fa Vang","type":"Huy\u1ec7n","location":"16 27 20N, 107 42 28E","provinceid":"46"}, {"districtid":"479","name":"H\u01b0\u01a1ng Th\u1ee7y","type":"Huy\u1ec7n","location":"16 19 27N, 107 37 26E","provinceid":"46"}, {"districtid":"480","name":"H\u01b0\u01a1ng Tr\u00e0","type":"Huy\u1ec7n","location":"16 25 49N, 107 28 37E","provinceid":"46"}, {"districtid":"481","name":"A L\u01b0\u1edbi","type":"Huy\u1ec7n","location":"16 13 59N, 107 16 12E","provinceid":"46"}, {"districtid":"482","name":"Ph\u00fa L\u1ed9c","type":"Huy\u1ec7n","location":"16 17 16N, 107 55 25E","provinceid":"46"}, {"districtid":"483","name":"Nam \u0110\u00f4ng","type":"Huy\u1ec7n","location":"16 07 11N, 107 41 25E","provinceid":"46"}, {"districtid":"490","name":"Li\u00ean Chi\u1ec3u","type":"Qu\u1eadn","location":"16 07 26N, 108 07 04E","provinceid":"48"}, {"districtid":"491","name":"Thanh Kh\u00ea","type":"Qu\u1eadn","location":"16 03 28N, 108 11 00E","provinceid":"48"}, {"districtid":"492","name":"H\u1ea3i Ch\u00e2u","type":"Qu\u1eadn","location":"16 03 38N, 108 11 46E","provinceid":"48"}, {"districtid":"493","name":"S\u01a1n Tr\u00e0","type":"Qu\u1eadn","location":"16 06 13N, 108 16 26E","provinceid":"48"}, {"districtid":"494","name":"Ng\u0169 H\u00e0nh S\u01a1n","type":"Qu\u1eadn","location":"16 00 30N, 108 15 09E","provinceid":"48"}, {"districtid":"495","name":"C\u1ea9m L\u1ec7","type":"Qu\u1eadn","location":"","provinceid":"48"}, {"districtid":"497","name":"Ho\u00e0 Vang","type":"Huy\u1ec7n","location":"16 03 59N, 108 01 57E","provinceid":"48"}, {"districtid":"498","name":"Ho\u00e0ng Sa","type":"Huy\u1ec7n","location":"16 21 36N, 111 57 01E","provinceid":"48"}, {"districtid":"502","name":"Tam K\u1ef3","type":"Th\u00e0nh Ph\u1ed1","location":"15 34 37N, 108 29 52E","provinceid":"49"}, {"districtid":"503","name":"H\u1ed9i An","type":"Th\u00e0nh Ph\u1ed1","location":"15 53 20N, 108 20 42E","provinceid":"49"}, {"districtid":"504","name":"T\u00e2y Giang","type":"Huy\u1ec7n","location":"15 53 46N, 107 25 52E","provinceid":"49"}, {"districtid":"505","name":"\u0110\u00f4ng Giang","type":"Huy\u1ec7n","location":"15 54 44N, 107 47 06E","provinceid":"49"}, {"districtid":"506","name":"\u0110\u1ea1i L\u1ed9c","type":"Huy\u1ec7n","location":"15 50 10N, 107 58 27E","provinceid":"49"}, {"districtid":"507","name":"\u0110i\u1ec7n B\u00e0n","type":"Huy\u1ec7n","location":"15 54 15N, 108 13 38E","provinceid":"49"}, {"districtid":"508","name":"Duy Xuy\u00ean","type":"Huy\u1ec7n","location":"15 47 58N, 108 13 27E","provinceid":"49"}, {"districtid":"509","name":"Qu\u1ebf S\u01a1n","type":"Huy\u1ec7n","location":"15 41 03N, 108 05 34E","provinceid":"49"}, {"districtid":"510","name":"Nam Giang","type":"Huy\u1ec7n","location":"15 36 37N, 107 33 52E","provinceid":"49"}, {"districtid":"511","name":"Ph\u01b0\u1edbc S\u01a1n","type":"Huy\u1ec7n","location":"15 23 17N, 107 50 22E","provinceid":"49"}, {"districtid":"512","name":"Hi\u1ec7p \u0110\u1ee9c","type":"Huy\u1ec7n","location":"15 31 09N, 108 05 56E","provinceid":"49"}, {"districtid":"513","name":"Th\u0103ng B\u00ecnh","type":"Huy\u1ec7n","location":"15 42 29N, 108 22 04E","provinceid":"49"}, {"districtid":"514","name":"Ti\u00ean Ph\u01b0\u1edbc","type":"Huy\u1ec7n","location":"15 29 30N, 108 15 28E","provinceid":"49"}, {"districtid":"515","name":"B\u1eafc Tr\u00e0 My","type":"Huy\u1ec7n","location":"15 08 00N, 108 05 32E","provinceid":"49"}, {"districtid":"516","name":"Nam Tr\u00e0 My","type":"Huy\u1ec7n","location":"15 16 40N, 108 12 15E","provinceid":"49"}, {"districtid":"517","name":"N\u00fai Th\u00e0nh","type":"Huy\u1ec7n","location":"15 26 53N, 108 34 49E","provinceid":"49"}, {"districtid":"518","name":"Ph\u00fa Ninh","type":"Huy\u1ec7n","location":"15 30 43N, 108 24 43E","provinceid":"49"}, {"districtid":"519","name":"N\u00f4ng S\u01a1n","type":"Huy\u1ec7n","location":"","provinceid":"49"}, {"districtid":"522","name":"Qu\u1ea3ng Ng\u00e3i","type":"Th\u00e0nh Ph\u1ed1","location":"15 07 17N, 108 48 24E","provinceid":"51"}, {"districtid":"524","name":"B\u00ecnh S\u01a1n","type":"Huy\u1ec7n","location":"15 18 45N, 108 45 35E","provinceid":"51"}, {"districtid":"525","name":"Tr\u00e0 B\u1ed3ng","type":"Huy\u1ec7n","location":"15 13 30N, 108 29 57E","provinceid":"51"}, {"districtid":"526","name":"T\u00e2y Tr\u00e0","type":"Huy\u1ec7n","location":"15 11 13N, 108 22 23E","provinceid":"51"}, {"districtid":"527","name":"S\u01a1n T\u1ecbnh","type":"Huy\u1ec7n","location":"15 11 49N, 108 45 03E","provinceid":"51"}, {"districtid":"528","name":"T\u01b0 Ngh\u0129a","type":"Huy\u1ec7n","location":"15 05 25N, 108 45 23E","provinceid":"51"}, {"districtid":"529","name":"S\u01a1n H\u00e0","type":"Huy\u1ec7n","location":"14 58 35N, 108 29 09E","provinceid":"51"}, {"districtid":"530","name":"S\u01a1n T\u00e2y","type":"Huy\u1ec7n","location":"14 58 11N, 108 21 22E","provinceid":"51"}, {"districtid":"531","name":"Minh Long","type":"Huy\u1ec7n","location":"14 56 49N, 108 40 19E","provinceid":"51"}, {"districtid":"532","name":"Ngh\u0129a H\u00e0nh","type":"Huy\u1ec7n","location":"14 58 06N, 108 46 05E","provinceid":"51"}, {"districtid":"533","name":"M\u1ed9 \u0110\u1ee9c","type":"Huy\u1ec7n","location":"11 59 13N, 108 52 21E","provinceid":"51"}, {"districtid":"534","name":"\u0110\u1ee9c Ph\u1ed5","type":"Huy\u1ec7n","location":"14 44 59N, 108 56 58E","provinceid":"51"}, {"districtid":"535","name":"Ba T\u01a1","type":"Huy\u1ec7n","location":"14 42 52N, 108 43 44E","provinceid":"51"}, {"districtid":"536","name":"L\u00fd S\u01a1n","type":"Huy\u1ec7n","location":"15 22 50N, 109 06 56E","provinceid":"51"}, {"districtid":"540","name":"Qui Nh\u01a1n","type":"Th\u00e0nh Ph\u1ed1","location":"13 47 15N, 109 12 48E","provinceid":"52"}, {"districtid":"542","name":"An L\u00e3o","type":"Huy\u1ec7n","location":"14 32 10N, 108 47 52E","provinceid":"52"}, {"districtid":"543","name":"Ho\u00e0i Nh\u01a1n","type":"Huy\u1ec7n","location":"14 30 56N, 109 01 56E","provinceid":"52"}, {"districtid":"544","name":"Ho\u00e0i \u00c2n","type":"Huy\u1ec7n","location":"14 20 51N, 108 54 04E","provinceid":"52"}, {"districtid":"545","name":"Ph\u00f9 M\u1ef9","type":"Huy\u1ec7n","location":"14 14 41N, 109 05 43E","provinceid":"52"}, {"districtid":"546","name":"V\u0129nh Th\u1ea1nh","type":"Huy\u1ec7n","location":"14 14 26N, 108 44 08E","provinceid":"52"}, {"districtid":"547","name":"T\u00e2y S\u01a1n","type":"Huy\u1ec7n","location":"13 56 47N, 108 53 06E","provinceid":"52"}, {"districtid":"548","name":"Ph\u00f9 C\u00e1t","type":"Huy\u1ec7n","location":"14 03 48N, 109 03 57E","provinceid":"52"}, {"districtid":"549","name":"An Nh\u01a1n","type":"Huy\u1ec7n","location":"13 51 28N, 109 04 02E","provinceid":"52"}, {"districtid":"550","name":"Tuy Ph\u01b0\u1edbc","type":"Huy\u1ec7n","location":"13 46 30N, 109 05 38E","provinceid":"52"}, {"districtid":"551","name":"V\u00e2n Canh","type":"Huy\u1ec7n","location":"13 40 35N, 108 57 52E","provinceid":"52"}, {"districtid":"555","name":"Tuy H\u00f2a","type":"Th\u00e0nh Ph\u1ed1","location":"13 05 42N, 109 15 50E","provinceid":"54"}, {"districtid":"557","name":"S\u00f4ng C\u1ea7u","type":"Th\u1ecb X\u00e3","location":"13 31 40N, 109 12 39E","provinceid":"54"}, {"districtid":"558","name":"\u0110\u1ed3ng Xu\u00e2n","type":"Huy\u1ec7n","location":"13 24 59N, 108 56 46E","provinceid":"54"}, {"districtid":"559","name":"Tuy An","type":"Huy\u1ec7n","location":"13 15 19N, 109 12 21E","provinceid":"54"}, {"districtid":"560","name":"S\u01a1n H\u00f2a","type":"Huy\u1ec7n","location":"13 12 16N, 108 57 17E","provinceid":"54"}, {"districtid":"561","name":"S\u00f4ng Hinh","type":"Huy\u1ec7n","location":"12 54 19N, 108 53 38E","provinceid":"54"}, {"districtid":"562","name":"T\u00e2y Ho\u00e0","type":"Huy\u1ec7n","location":"","provinceid":"54"}, {"districtid":"563","name":"Ph\u00fa Ho\u00e0","type":"Huy\u1ec7n","location":"13 04 07N, 109 11 24E","provinceid":"54"}, {"districtid":"564","name":"\u0110\u00f4ng Ho\u00e0","type":"Huy\u1ec7n","location":"","provinceid":"54"}, {"districtid":"568","name":"Nha Trang","type":"Th\u00e0nh Ph\u1ed1","location":"12 15 40N, 109 10 40E","provinceid":"56"}, {"districtid":"569","name":"Cam Ranh","type":"Th\u1ecb X\u00e3","location":"11 59 05N, 108 08 17E","provinceid":"56"}, {"districtid":"570","name":"Cam L\u00e2m","type":"Huy\u1ec7n","location":"","provinceid":"56"}, {"districtid":"571","name":"V\u1ea1n Ninh","type":"Huy\u1ec7n","location":"12 43 10N, 109 11 18E","provinceid":"56"}, {"districtid":"572","name":"Ninh H\u00f2a","type":"Huy\u1ec7n","location":"12 32 54N, 109 06 11E","provinceid":"56"}, {"districtid":"573","name":"Kh\u00e1nh V\u0129nh","type":"Huy\u1ec7n","location":"12 17 50N, 108 51 56E","provinceid":"56"}, {"districtid":"574","name":"Di\u00ean Kh\u00e1nh","type":"Huy\u1ec7n","location":"12 13 19N, 109 02 16E","provinceid":"56"}, {"districtid":"575","name":"Kh\u00e1nh S\u01a1n","type":"Huy\u1ec7n","location":"12 02 17N, 108 53 47E","provinceid":"56"}, {"districtid":"576","name":"Tr\u01b0\u1eddng Sa","type":"Huy\u1ec7n","location":"9 07 27N, 114 15 00E","provinceid":"56"}, {"districtid":"582","name":"Phan Rang-Th\u00e1p Ch\u00e0m","type":"Th\u00e0nh Ph\u1ed1","location":"11 36 11N, 108 58 34E","provinceid":"58"}, {"districtid":"584","name":"B\u00e1c \u00c1i","type":"Huy\u1ec7n","location":"11 54 45N, 108 51 29E","provinceid":"58"}, {"districtid":"585","name":"Ninh S\u01a1n","type":"Huy\u1ec7n","location":"11 42 36N, 108 44 55E","provinceid":"58"}, {"districtid":"586","name":"Ninh H\u1ea3i","type":"Huy\u1ec7n","location":"11 42 46N, 109 05 41E","provinceid":"58"}, {"districtid":"587","name":"Ninh Ph\u01b0\u1edbc","type":"Huy\u1ec7n","location":"11 28 56N, 108 50 34E","provinceid":"58"}, {"districtid":"588","name":"Thu\u1eadn B\u1eafc","type":"Huy\u1ec7n","location":"","provinceid":"58"}, {"districtid":"589","name":"Thu\u1eadn Nam","type":"Huy\u1ec7n","location":"","provinceid":"58"}, {"districtid":"593","name":"Phan Thi\u1ebft","type":"Th\u00e0nh Ph\u1ed1","location":"10 54 16N, 108 03 44E","provinceid":"60"}, {"districtid":"594","name":"La Gi","type":"Th\u1ecb X\u00e3","location":"","provinceid":"60"}, {"districtid":"595","name":"Tuy Phong","type":"Huy\u1ec7n","location":"11 20 26N, 108 41 15E","provinceid":"60"}, {"districtid":"596","name":"B\u1eafc B\u00ecnh","type":"Huy\u1ec7n","location":"11 15 52N, 108 21 33E","provinceid":"60"}, {"districtid":"597","name":"H\u00e0m Thu\u1eadn B\u1eafc","type":"Huy\u1ec7n","location":"11 09 18N, 108 03 07E","provinceid":"60"}, {"districtid":"598","name":"H\u00e0m Thu\u1eadn Nam","type":"Huy\u1ec7n","location":"10 56 20N, 107 54 38E","provinceid":"60"}, {"districtid":"599","name":"T\u00e1nh Linh","type":"Huy\u1ec7n","location":"11 08 26N, 107 41 22E","provinceid":"60"}, {"districtid":"600","name":"\u0110\u1ee9c Linh","type":"Huy\u1ec7n","location":"11 11 43N, 107 31 34E","provinceid":"60"}, {"districtid":"601","name":"H\u00e0m T\u00e2n","type":"Huy\u1ec7n","location":"10 44 41N, 107 41 33E","provinceid":"60"}, {"districtid":"602","name":"Ph\u00fa Qu\u00ed","type":"Huy\u1ec7n","location":"10 33 13N, 108 57 46E","provinceid":"60"}, {"districtid":"608","name":"Kon Tum","type":"Th\u00e0nh Ph\u1ed1","location":"14 20 32N, 107 58 04E","provinceid":"62"}, {"districtid":"610","name":"\u0110\u1eafk Glei","type":"Huy\u1ec7n","location":"15 08 13N, 107 44 03E","provinceid":"62"}, {"districtid":"611","name":"Ng\u1ecdc H\u1ed3i","type":"Huy\u1ec7n","location":"14 44 23N, 107 38 49E","provinceid":"62"}, {"districtid":"612","name":"\u0110\u1eafk T\u00f4","type":"Huy\u1ec7n","location":"14 46 49N, 107 55 36E","provinceid":"62"}, {"districtid":"613","name":"Kon Pl\u00f4ng","type":"Huy\u1ec7n","location":"14 48 13N, 108 20 05E","provinceid":"62"}, {"districtid":"614","name":"Kon R\u1eaby","type":"Huy\u1ec7n","location":"14 32 56N, 108 13 09E","provinceid":"62"}, {"districtid":"615","name":"\u0110\u1eafk H\u00e0","type":"Huy\u1ec7n","location":"14 36 50N, 107 59 55E","provinceid":"62"}, {"districtid":"616","name":"Sa Th\u1ea7y","type":"Huy\u1ec7n","location":"14 16 02N, 107 36 30E","provinceid":"62"}, {"districtid":"617","name":"Tu M\u01a1 R\u00f4ng","type":"Huy\u1ec7n","location":"","provinceid":"62"}, {"districtid":"622","name":"Pleiku","type":"Th\u00e0nh Ph\u1ed1","location":"13 57 42N, 107 58 03E","provinceid":"64"}, {"districtid":"623","name":"An Kh\u00ea","type":"Th\u1ecb X\u00e3","location":"14 01 24N, 108 41 29E","provinceid":"64"}, {"districtid":"624","name":"Ayun Pa","type":"Th\u1ecb X\u00e3","location":"","provinceid":"64"}, {"districtid":"625","name":"Kbang","type":"Huy\u1ec7n","location":"14 18 08N, 108 29 17E","provinceid":"64"}, {"districtid":"626","name":"\u0110\u0103k \u0110oa","type":"Huy\u1ec7n","location":"14 07 02N, 108 09 36E","provinceid":"64"}, {"districtid":"627","name":"Ch\u01b0 P\u0103h","type":"Huy\u1ec7n","location":"14 13 30N, 107 56 33E","provinceid":"64"}, {"districtid":"628","name":"Ia Grai","type":"Huy\u1ec7n","location":"13 59 25N, 107 43 16E","provinceid":"64"}, {"districtid":"629","name":"Mang Yang","type":"Huy\u1ec7n","location":"13 57 26N, 108 18 37E","provinceid":"64"}, {"districtid":"630","name":"K\u00f4ng Chro","type":"Huy\u1ec7n","location":"13 45 47N, 108 36 04E","provinceid":"64"}, {"districtid":"631","name":"\u0110\u1ee9c C\u01a1","type":"Huy\u1ec7n","location":"13 46 16N, 107 38 26E","provinceid":"64"}, {"districtid":"632","name":"Ch\u01b0 Pr\u00f4ng","type":"Huy\u1ec7n","location":"13 35 39N, 107 47 36E","provinceid":"64"}, {"districtid":"633","name":"Ch\u01b0 S\u00ea","type":"Huy\u1ec7n","location":"13 37 04N, 108 06 56E","provinceid":"64"}, {"districtid":"634","name":"\u0110\u0103k P\u01a1","type":"Huy\u1ec7n","location":"13 55 47N, 108 36 16E","provinceid":"64"}, {"districtid":"635","name":"Ia Pa","type":"Huy\u1ec7n","location":"13 31 37N, 108 30 34E","provinceid":"64"}, {"districtid":"637","name":"Kr\u00f4ng Pa","type":"Huy\u1ec7n","location":"13 14 13N, 108 39 12E","provinceid":"64"}, {"districtid":"638","name":"Ph\u00fa Thi\u1ec7n","type":"Huy\u1ec7n","location":"","provinceid":"64"}, {"districtid":"639","name":"Ch\u01b0 P\u01b0h","type":"Huy\u1ec7n","location":"","provinceid":"64"}, {"districtid":"643","name":"Bu\u00f4n Ma Thu\u1ed9t","type":"Th\u00e0nh Ph\u1ed1","location":"12 39 43N, 108 10 40E","provinceid":"66"}, {"districtid":"644","name":"Bu\u00f4n H\u1ed3","type":"Th\u1ecb X\u00e3","location":"","provinceid":"66"}, {"districtid":"645","name":"Ea H'leo","type":"Huy\u1ec7n","location":"13 13 52N, 108 12 30E","provinceid":"66"}, {"districtid":"646","name":"Ea S\u00fap","type":"Huy\u1ec7n","location":"13 10 59N, 107 46 49E","provinceid":"66"}, {"districtid":"647","name":"Bu\u00f4n \u0110\u00f4n","type":"Huy\u1ec7n","location":"12 52 45N, 107 45 20E","provinceid":"66"}, {"districtid":"648","name":"C\u01b0 M'gar","type":"Huy\u1ec7n","location":"12 53 47N, 108 04 16E","provinceid":"66"}, {"districtid":"649","name":"Kr\u00f4ng B\u00fak","type":"Huy\u1ec7n","location":"12 56 27N, 108 13 54E","provinceid":"66"}, {"districtid":"650","name":"Kr\u00f4ng N\u0103ng","type":"Huy\u1ec7n","location":"12 59 41N, 108 23 42E","provinceid":"66"}, {"districtid":"651","name":"Ea Kar","type":"Huy\u1ec7n","location":"12 48 17N, 108 32 42E","provinceid":"66"}, {"districtid":"652","name":"M'\u0111r\u1eafk","type":"Huy\u1ec7n","location":"12 42 14N, 108 47 09E","provinceid":"66"}, {"districtid":"653","name":"Kr\u00f4ng B\u00f4ng","type":"Huy\u1ec7n","location":"12 27 08N, 108 27 01E","provinceid":"66"}, {"districtid":"654","name":"Kr\u00f4ng P\u1eafc","type":"Huy\u1ec7n","location":"12 41 20N, 108 18 42E","provinceid":"66"}, {"districtid":"655","name":"Kr\u00f4ng A Na","type":"Huy\u1ec7n","location":"12 31 51N, 108 05 03E","provinceid":"66"}, {"districtid":"656","name":"L\u1eafk","type":"Huy\u1ec7n","location":"12 19 20N, 108 12 17E","provinceid":"66"}, {"districtid":"657","name":"C\u01b0 Kuin","type":"Huy\u1ec7n","location":"","provinceid":"66"}, {"districtid":"660","name":"Gia Ngh\u0129a","type":"Th\u1ecb X\u00e3","location":"","provinceid":"67"}, {"districtid":"661","name":"\u0110\u1eafk Glong","type":"Huy\u1ec7n","location":"12 01 53N, 107 50 37E","provinceid":"67"}, {"districtid":"662","name":"C\u01b0 J\u00fat","type":"Huy\u1ec7n","location":"12 40 56N, 107 44 44E","provinceid":"67"}, {"districtid":"663","name":"\u0110\u1eafk Mil","type":"Huy\u1ec7n","location":"12 31 08N, 107 42 24E","provinceid":"67"}, {"districtid":"664","name":"Kr\u00f4ng N\u00f4","type":"Huy\u1ec7n","location":"12 22 16N, 107 53 49E","provinceid":"67"}, {"districtid":"665","name":"\u0110\u1eafk Song","type":"Huy\u1ec7n","location":"12 14 04N, 107 36 30E","provinceid":"67"}, {"districtid":"666","name":"\u0110\u1eafk R'l\u1ea5p","type":"Huy\u1ec7n","location":"12 02 30N, 107 25 59E","provinceid":"67"}, {"districtid":"667","name":"Tuy \u0110\u1ee9c","type":"Huy\u1ec7n","location":"","provinceid":"67"}, {"districtid":"672","name":"\u0110\u00e0 L\u1ea1t","type":"Th\u00e0nh Ph\u1ed1","location":"11 54 33N, 108 27 08E","provinceid":"68"}, {"districtid":"673","name":"B\u1ea3o L\u1ed9c","type":"Th\u1ecb X\u00e3","location":"11 32 48N, 107 47 37E","provinceid":"68"}, {"districtid":"674","name":"\u0110am R\u00f4ng","type":"Huy\u1ec7n","location":"12 02 35N, 108 10 26E","provinceid":"68"}, {"districtid":"675","name":"L\u1ea1c D\u01b0\u01a1ng","type":"Huy\u1ec7n","location":"12 08 30N, 108 27 48E","provinceid":"68"}, {"districtid":"676","name":"L\u00e2m H\u00e0","type":"Huy\u1ec7n","location":"11 55 26N, 108 11 31E","provinceid":"68"}, {"districtid":"677","name":"\u0110\u01a1n D\u01b0\u01a1ng","type":"Huy\u1ec7n","location":"11 48 26N, 108 32 48E","provinceid":"68"}, {"districtid":"678","name":"\u0110\u1ee9c Tr\u1ecdng","type":"Huy\u1ec7n","location":"11 41 50N, 108 18 58E","provinceid":"68"}, {"districtid":"679","name":"Di Linh","type":"Huy\u1ec7n","location":"11 31 10N, 108 05 23E","provinceid":"68"}, {"districtid":"680","name":"B\u1ea3o L\u00e2m","type":"Huy\u1ec7n","location":"11 38 31N, 107 43 25E","provinceid":"68"}, {"districtid":"681","name":"\u0110\u1ea1 Huoai","type":"Huy\u1ec7n","location":"11 27 11N, 107 38 08E","provinceid":"68"}, {"districtid":"682","name":"\u0110\u1ea1 T\u1ebbh","type":"Huy\u1ec7n","location":"11 33 46N, 107 32 00E","provinceid":"68"}, {"districtid":"683","name":"C\u00e1t Ti\u00ean","type":"Huy\u1ec7n","location":"11 39 38N, 107 23 27E","provinceid":"68"}, {"districtid":"688","name":"Ph\u01b0\u1edbc Long","type":"Th\u1ecb X\u00e3","location":"","provinceid":"70"}, {"districtid":"689","name":"\u0110\u1ed3ng Xo\u00e0i","type":"Th\u1ecb X\u00e3","location":"11 31 01N, 106 50 21E","provinceid":"70"}, {"districtid":"690","name":"B\u00ecnh Long","type":"Th\u1ecb X\u00e3","location":"","provinceid":"70"}, {"districtid":"691","name":"B\u00f9 Gia M\u1eadp","type":"Huy\u1ec7n","location":"11 56 57N, 106 59 21E","provinceid":"70"}, {"districtid":"692","name":"L\u1ed9c Ninh","type":"Huy\u1ec7n","location":"11 49 28N, 106 35 11E","provinceid":"70"}, {"districtid":"693","name":"B\u00f9 \u0110\u1ed1p","type":"Huy\u1ec7n","location":"11 59 08N, 106 49 54E","provinceid":"70"}, {"districtid":"694","name":"H\u1edbn Qu\u1ea3n","type":"Huy\u1ec7n","location":"11 37 37N, 106 36 02E","provinceid":"70"}, {"districtid":"695","name":"\u0110\u1ed3ng Ph\u00f9","type":"Huy\u1ec7n","location":"11 28 45N, 106 57 07E","provinceid":"70"}, {"districtid":"696","name":"B\u00f9 \u0110\u0103ng","type":"Huy\u1ec7n","location":"11 46 09N, 107 14 14E","provinceid":"70"}, {"districtid":"697","name":"Ch\u01a1n Th\u00e0nh","type":"Huy\u1ec7n","location":"11 28 45N, 106 39 26E","provinceid":"70"}, {"districtid":"703","name":"T\u00e2y Ninh","type":"Th\u1ecb X\u00e3","location":"11 21 59N, 106 07 47E","provinceid":"72"}, {"districtid":"705","name":"T\u00e2n Bi\u00ean","type":"Huy\u1ec7n","location":"11 35 14N, 105 57 53E","provinceid":"72"}, {"districtid":"706","name":"T\u00e2n Ch\u00e2u","type":"Huy\u1ec7n","location":"11 34 49N, 106 17 48E","provinceid":"72"}, {"districtid":"707","name":"D\u01b0\u01a1ng Minh Ch\u00e2u","type":"Huy\u1ec7n","location":"11 22 04N, 106 16 58E","provinceid":"72"}, {"districtid":"708","name":"Ch\u00e2u Th\u00e0nh","type":"Huy\u1ec7n","location":"11 19 02N, 106 00 15E","provinceid":"72"}, {"districtid":"709","name":"H\u00f2a Th\u00e0nh","type":"Huy\u1ec7n","location":"11 15 31N, 106 08 44E","provinceid":"72"}, {"districtid":"710","name":"G\u00f2 D\u1ea7u","type":"Huy\u1ec7n","location":"11 09 39N, 106 14 42E","provinceid":"72"}, {"districtid":"711","name":"B\u1ebfn C\u1ea7u","type":"Huy\u1ec7n","location":"11 07 50N, 106 08 25E","provinceid":"72"}, {"districtid":"712","name":"Tr\u1ea3ng B\u00e0ng","type":"Huy\u1ec7n","location":"11 06 18N, 106 23 12E","provinceid":"72"}, {"districtid":"718","name":"Th\u1ee7 D\u1ea7u M\u1ed9t","type":"Th\u1ecb X\u00e3","location":"11 00 01N, 106 38 56E","provinceid":"74"}, {"districtid":"720","name":"D\u1ea7u Ti\u1ebfng","type":"Huy\u1ec7n","location":"11 19 07N, 106 26 59E","provinceid":"74"}, {"districtid":"721","name":"B\u1ebfn C\u00e1t","type":"Huy\u1ec7n","location":"11 12 42N, 106 36 28E","provinceid":"74"}, {"districtid":"722","name":"Ph\u00fa Gi\u00e1o","type":"Huy\u1ec7n","location":"11 20 21N, 106 47 48E","provinceid":"74"}, {"districtid":"723","name":"T\u00e2n Uy\u00ean","type":"Huy\u1ec7n","location":"11 06 31N, 106 49 02E","provinceid":"74"}, {"districtid":"724","name":"D\u0129 An","type":"Huy\u1ec7n","location":"10 55 03N, 106 47 09E","provinceid":"74"}, {"districtid":"725","name":"Thu\u1eadn An","type":"Huy\u1ec7n","location":"10 55 58N, 106 41 59E","provinceid":"74"}, {"districtid":"731","name":"Bi\u00ean H\u00f2a","type":"Th\u00e0nh Ph\u1ed1","location":"10 56 31N, 106 50 50E","provinceid":"75"}, {"districtid":"732","name":"Long Kh\u00e1nh","type":"Th\u1ecb X\u00e3","location":"10 56 24N, 107 14 29E","provinceid":"75"}, {"districtid":"734","name":"T\u00e2n Ph\u00fa","type":"Huy\u1ec7n","location":"11 22 51N, 107 21 35E","provinceid":"75"}, {"districtid":"735","name":"V\u0129nh C\u1eedu","type":"Huy\u1ec7n","location":"11 14 31N, 107 00 06E","provinceid":"75"}, {"districtid":"736","name":"\u0110\u1ecbnh Qu\u00e1n","type":"Huy\u1ec7n","location":"11 12 41N, 107 17 03E","provinceid":"75"}, {"districtid":"737","name":"Tr\u1ea3ng Bom","type":"Huy\u1ec7n","location":"10 58 39N, 107 00 52E","provinceid":"75"}, {"districtid":"738","name":"Th\u1ed1ng Nh\u1ea5t","type":"Huy\u1ec7n","location":"10 58 29N, 107 09 26E","provinceid":"75"}, {"districtid":"739","name":"C\u1ea9m M\u1ef9","type":"Huy\u1ec7n","location":"10 47 05N, 107 14 36E","provinceid":"75"}, {"districtid":"740","name":"Long Th\u00e0nh","type":"Huy\u1ec7n","location":"10 47 38N, 106 59 42E","provinceid":"75"}, {"districtid":"741","name":"Xu\u00e2n L\u1ed9c","type":"Huy\u1ec7n","location":"10 55 39N, 107 24 21E","provinceid":"75"}, {"districtid":"742","name":"Nh\u01a1n Tr\u1ea1ch","type":"Huy\u1ec7n","location":"10 39 18N, 106 53 18E","provinceid":"75"}, {"districtid":"747","name":"V\u0169ng T\u1ea7u","type":"Th\u00e0nh Ph\u1ed1","location":"10 24 08N, 107 07 05E","provinceid":"77"}, {"districtid":"748","name":"B\u00e0 R\u1ecba","type":"Th\u1ecb X\u00e3","location":"10 30 33N, 107 10 47E","provinceid":"77"}, {"districtid":"750","name":"Ch\u00e2u \u0110\u1ee9c","type":"Huy\u1ec7n","location":"10 39 23N, 107 15 08E","provinceid":"77"}, {"districtid":"751","name":"Xuy\u00ean M\u1ed9c","type":"Huy\u1ec7n","location":"10 37 46N, 107 29 39E","provinceid":"77"}, {"districtid":"752","name":"Long \u0110i\u1ec1n","type":"Huy\u1ec7n","location":"10 26 47N, 107 12 53E","provinceid":"77"}, {"districtid":"753","name":"\u0110\u1ea5t \u0110\u1ecf","type":"Huy\u1ec7n","location":"10 28 40N, 107 18 27E","provinceid":"77"}, {"districtid":"754","name":"T\u00e2n Th\u00e0nh","type":"Huy\u1ec7n","location":"10 34 50N, 107 05 06E","provinceid":"77"}, {"districtid":"755","name":"C\u00f4n \u0110\u1ea3o","type":"Huy\u1ec7n","location":"8 42 25N, 106 36 05E","provinceid":"77"}, {"districtid":"760","name":"1","type":"Qu\u1eadn","location":"10 46 34N, 106 41 45E","provinceid":"79"}, {"districtid":"761","name":"12","type":"Qu\u1eadn","location":"10 51 43N, 106 39 32E","provinceid":"79"}, {"districtid":"762","name":"Th\u1ee7 \u0110\u1ee9c","type":"Qu\u1eadn","location":"10 51 20N, 106 45 05E","provinceid":"79"}, {"districtid":"763","name":"9","type":"Qu\u1eadn","location":"10 49 49N, 106 49 03E","provinceid":"79"}, {"districtid":"764","name":"G\u00f2 V\u1ea5p","type":"Qu\u1eadn","location":"10 50 12N, 106 39 52E","provinceid":"79"}, {"districtid":"765","name":"B\u00ecnh Th\u1ea1nh","type":"Qu\u1eadn","location":"10 48 46N, 106 42 57E","provinceid":"79"}, {"districtid":"766","name":"T\u00e2n B\u00ecnh","type":"Qu\u1eadn","location":"10 48 13N, 106 39 03E","provinceid":"79"}, {"districtid":"767","name":"T\u00e2n Ph\u00fa","type":"Qu\u1eadn","location":"10 47 32N, 106 37 31E","provinceid":"79"}, {"districtid":"768","name":"Ph\u00fa Nhu\u1eadn","type":"Qu\u1eadn","location":"10 48 06N, 106 40 39E","provinceid":"79"}, {"districtid":"769","name":"2","type":"Qu\u1eadn","location":"10 46 51N, 106 45 25E","provinceid":"79"}, {"districtid":"770","name":"3","type":"Qu\u1eadn","location":"10 46 48N, 106 40 46E","provinceid":"79"}, {"districtid":"771","name":"10","type":"Qu\u1eadn","location":"10 46 25N, 106 40 02E","provinceid":"79"}, {"districtid":"772","name":"11","type":"Qu\u1eadn","location":"10 46 01N, 106 38 44E","provinceid":"79"}, {"districtid":"773","name":"4","type":"Qu\u1eadn","location":"10 45 42N, 106 42 09E","provinceid":"79"}, {"districtid":"774","name":"5","type":"Qu\u1eadn","location":"10 45 24N, 106 40 00E","provinceid":"79"}, {"districtid":"775","name":"6","type":"Qu\u1eadn","location":"10 44 46N, 106 38 10E","provinceid":"79"}, {"districtid":"776","name":"8","type":"Qu\u1eadn","location":"10 43 24N, 106 37 40E","provinceid":"79"}, {"districtid":"777","name":"B\u00ecnh T\u00e2n","type":"Qu\u1eadn","location":"10 46 16N, 106 35 26E","provinceid":"79"}, {"districtid":"778","name":"7","type":"Qu\u1eadn","location":"10 44 19N, 106 43 35E","provinceid":"79"}, {"districtid":"783","name":"C\u1ee7 Chi","type":"Huy\u1ec7n","location":"11 02 17N, 106 30 20E","provinceid":"79"}, {"districtid":"784","name":"H\u00f3c M\u00f4n","type":"Huy\u1ec7n","location":"10 52 42N, 106 35 33E","provinceid":"79"}, {"districtid":"785","name":"B\u00ecnh Ch\u00e1nh","type":"Huy\u1ec7n","location":"10 45 01N, 106 30 45E","provinceid":"79"}, {"districtid":"786","name":"Nh\u00e0 B\u00e8","type":"Huy\u1ec7n","location":"10 39 06N, 106 43 35E","provinceid":"79"}, {"districtid":"787","name":"C\u1ea7n Gi\u1edd","type":"Huy\u1ec7n","location":"10 30 43N, 106 52 50E","provinceid":"79"}, {"districtid":"794","name":"T\u00e2n An","type":"Th\u00e0nh Ph\u1ed1","location":"10 31 36N, 106 24 06E","provinceid":"80"}, {"districtid":"796","name":"T\u00e2n H\u01b0ng","type":"Huy\u1ec7n","location":"10 49 05N, 105 39 26E","provinceid":"80"}, {"districtid":"797","name":"V\u0129nh H\u01b0ng","type":"Huy\u1ec7n","location":"10 52 54N, 105 45 58E","provinceid":"80"}, {"districtid":"798","name":"M\u1ed9c H\u00f3a","type":"Huy\u1ec7n","location":"10 47 09N, 105 57 56E","provinceid":"80"}, {"districtid":"799","name":"T\u00e2n Th\u1ea1nh","type":"Huy\u1ec7n","location":"10 37 44N, 105 57 07E","provinceid":"80"}, {"districtid":"800","name":"Th\u1ea1nh H\u00f3a","type":"Huy\u1ec7n","location":"10 41 37N, 106 11 08E","provinceid":"80"}, {"districtid":"801","name":"\u0110\u1ee9c Hu\u1ec7","type":"Huy\u1ec7n","location":"10 51 57N, 106 15 48E","provinceid":"80"}, {"districtid":"802","name":"\u0110\u1ee9c H\u00f2a","type":"Huy\u1ec7n","location":"10 53 04N, 106 23 58E","provinceid":"80"}, {"districtid":"803","name":"B\u1ebfn L\u1ee9c","type":"Huy\u1ec7n","location":"10 41 40N, 106 26 28E","provinceid":"80"}, {"districtid":"804","name":"Th\u1ee7 Th\u1eeba","type":"Huy\u1ec7n","location":"10 39 41N, 106 20 12E","provinceid":"80"}, {"districtid":"805","name":"T\u00e2n Tr\u1ee5","type":"Huy\u1ec7n","location":"10 31 47N, 106 30 06E","provinceid":"80"}, {"districtid":"806","name":"C\u1ea7n \u0110\u01b0\u1edbc","type":"Huy\u1ec7n","location":"10 32 21N, 106 36 33E","provinceid":"80"}, {"districtid":"807","name":"C\u1ea7n Giu\u1ed9c","type":"Huy\u1ec7n","location":"10 34 43N, 106 38 35E","provinceid":"80"}, {"districtid":"808","name":"Ch\u00e2u Th\u00e0nh","type":"Huy\u1ec7n","location":"10 27 52N, 106 30 00E","provinceid":"80"}, {"districtid":"815","name":"M\u1ef9 Tho","type":"Th\u00e0nh Ph\u1ed1","location":"10 22 14N, 106 21 52E","provinceid":"82"}, {"districtid":"816","name":"G\u00f2 C\u00f4ng","type":"Th\u1ecb X\u00e3","location":"10 21 55N, 106 40 24E","provinceid":"82"}, {"districtid":"818","name":"T\u00e2n Ph\u01b0\u1edbc","type":"Huy\u1ec7n","location":"10 30 36N, 106 13 02E","provinceid":"82"}, {"districtid":"819","name":"C\u00e1i B\u00e8","type":"Huy\u1ec7n","location":"10 24 21N, 105 56 01E","provinceid":"82"}, {"districtid":"820","name":"Cai L\u1eady","type":"Huy\u1ec7n","location":"10 24 20N, 106 06 05E","provinceid":"82"}, {"districtid":"821","name":"Ch\u00e2u Th\u00e0nh","type":"Huy\u1ec7n","location":"20 25 21N, 106 16 57E","provinceid":"82"}, {"districtid":"822","name":"Ch\u1ee3 G\u1ea1o","type":"Huy\u1ec7n","location":"10 23 45N, 106 26 53E","provinceid":"82"}, {"districtid":"823","name":"G\u00f2 C\u00f4ng T\u00e2y","type":"Huy\u1ec7n","location":"10 19 55N, 106 35 02E","provinceid":"82"}, {"districtid":"824","name":"G\u00f2 C\u00f4ng \u0110\u00f4ng","type":"Huy\u1ec7n","location":"10 20 42N, 106 42 54E","provinceid":"82"}, {"districtid":"825","name":"T\u00e2n Ph\u00fa \u0110\u00f4ng","type":"Huy\u1ec7n","location":"","provinceid":"82"}, {"districtid":"829","name":"B\u1ebfn Tre","type":"Th\u00e0nh Ph\u1ed1","location":"10 14 17N, 106 22 26E","provinceid":"83"}, {"districtid":"831","name":"Ch\u00e2u Th\u00e0nh","type":"Huy\u1ec7n","location":"10 17 24N, 106 17 45E","provinceid":"83"}, {"districtid":"832","name":"Ch\u1ee3 L\u00e1ch","type":"Huy\u1ec7n","location":"10 13 26N, 106 09 08E","provinceid":"83"}, {"districtid":"833","name":"M\u1ecf C\u00e0y Nam","type":"Huy\u1ec7n","location":"10 06 56N, 106 19 40E","provinceid":"83"}, {"districtid":"834","name":"Gi\u1ed3ng Tr\u00f4m","type":"Huy\u1ec7n","location":"10 08 46N, 106 28 12E","provinceid":"83"}, {"districtid":"835","name":"B\u00ecnh \u0110\u1ea1i","type":"Huy\u1ec7n","location":"10 09 56N, 106 37 46E","provinceid":"83"}, {"districtid":"836","name":"Ba Tri","type":"Huy\u1ec7n","location":"10 04 08N, 106 35 10E","provinceid":"83"}, {"districtid":"837","name":"Th\u1ea1nh Ph\u00fa","type":"Huy\u1ec7n","location":"9 55 53N, 106 32 45E","provinceid":"83"}, {"districtid":"838","name":"M\u1ecf C\u00e0y B\u1eafc","type":"Huy\u1ec7n","location":"","provinceid":"83"}, {"districtid":"842","name":"Tr\u00e0 Vinh","type":"Th\u1ecb X\u00e3","location":"9 57 09N, 106 20 39E","provinceid":"84"}, {"districtid":"844","name":"C\u00e0ng Long","type":"Huy\u1ec7n","location":"9 58 18N, 106 12 52E","provinceid":"84"}, {"districtid":"845","name":"C\u1ea7u K\u00e8","type":"Huy\u1ec7n","location":"9 51 23N, 106 03 33E","provinceid":"84"}, {"districtid":"846","name":"Ti\u1ec3u C\u1ea7n","type":"Huy\u1ec7n","location":"9 48 37N, 106 12 06E","provinceid":"84"}, {"districtid":"847","name":"Ch\u00e2u Th\u00e0nh","type":"Huy\u1ec7n","location":"9 52 57N, 106 24 12E","provinceid":"84"}, {"districtid":"848","name":"C\u1ea7u Ngang","type":"Huy\u1ec7n","location":"9 47 14N, 106 29 19E","provinceid":"84"}, {"districtid":"849","name":"Tr\u00e0 C\u00fa","type":"Huy\u1ec7n","location":"9 42 06N, 106 16 24E","provinceid":"84"}, {"districtid":"850","name":"Duy\u00ean H\u1ea3i","type":"Huy\u1ec7n","location":"9 39 58N, 106 26 23E","provinceid":"84"}, {"districtid":"855","name":"V\u0129nh Long","type":"Th\u00e0nh Ph\u1ed1","location":"10 15 09N, 105 56 08E","provinceid":"86"}, {"districtid":"857","name":"Long H\u1ed3","type":"Huy\u1ec7n","location":"10 13 58N, 105 55 47E","provinceid":"86"}, {"districtid":"858","name":"Mang Th\u00edt","type":"Huy\u1ec7n","location":"10 10 58N, 106 05 13E","provinceid":"86"}, {"districtid":"859","name":"V\u0169ng Li\u00eam","type":"Huy\u1ec7n","location":"10 03 32N, 106 10 35E","provinceid":"86"}, {"districtid":"860","name":"Tam B\u00ecnh","type":"Huy\u1ec7n","location":"10 03 58N, 105 58 03E","provinceid":"86"}, {"districtid":"861","name":"B\u00ecnh Minh","type":"Huy\u1ec7n","location":"10 05 45N, 105 47 21E","provinceid":"86"}, {"districtid":"862","name":"Tr\u00e0 \u00d4n","type":"Huy\u1ec7n","location":"9 59 20N, 105 57 56E","provinceid":"86"}, {"districtid":"863","name":"B\u00ecnh T\u00e2n","type":"Huy\u1ec7n","location":"","provinceid":"86"}, {"districtid":"866","name":"Cao L\u00e3nh","type":"Th\u00e0nh Ph\u1ed1","location":"10 27 38N, 105 37 21E","provinceid":"87"}, {"districtid":"867","name":"Sa \u0110\u00e9c","type":"Th\u1ecb X\u00e3","location":"10 19 22N, 105 44 31E","provinceid":"87"}, {"districtid":"868","name":"H\u1ed3ng Ng\u1ef1","type":"Th\u1ecb X\u00e3","location":"","provinceid":"87"}, {"districtid":"869","name":"T\u00e2n H\u1ed3ng","type":"Huy\u1ec7n","location":"10 52 48N, 105 29 21E","provinceid":"87"}, {"districtid":"870","name":"H\u1ed3ng Ng\u1ef1","type":"Huy\u1ec7n","location":"10 48 13N, 105 19 00E","provinceid":"87"}, {"districtid":"871","name":"Tam N\u00f4ng","type":"Huy\u1ec7n","location":"10 44 06N, 105 30 58E","provinceid":"87"}, {"districtid":"872","name":"Th\u00e1p M\u01b0\u1eddi","type":"Huy\u1ec7n","location":"10 33 36N, 105 47 13E","provinceid":"87"}, {"districtid":"873","name":"Cao L\u00e3nh","type":"Huy\u1ec7n","location":"10 29 03N, 105 41 40E","provinceid":"87"}, {"districtid":"874","name":"Thanh B\u00ecnh","type":"Huy\u1ec7n","location":"10 36 38N, 105 28 51E","provinceid":"87"}, {"districtid":"875","name":"L\u1ea5p V\u00f2","type":"Huy\u1ec7n","location":"10 21 27N, 105 36 06E","provinceid":"87"}, {"districtid":"876","name":"Lai Vung","type":"Huy\u1ec7n","location":"10 14 43N, 105 38 40E","provinceid":"87"}, {"districtid":"877","name":"Ch\u00e2u Th\u00e0nh","type":"Huy\u1ec7n","location":"10 13 27N, 105 48 38E","provinceid":"87"}, {"districtid":"883","name":"Long Xuy\u00ean","type":"Th\u00e0nh Ph\u1ed1","location":"10 22 22N, 105 25 33E","provinceid":"89"}, {"districtid":"884","name":"Ch\u00e2u \u0110\u1ed1c","type":"Th\u1ecb X\u00e3","location":"10 41 20N, 105 05 15E","provinceid":"89"}, {"districtid":"886","name":"An Ph\u00fa","type":"Huy\u1ec7n","location":"10 50 12N, 105 05 33E","provinceid":"89"}, {"districtid":"887","name":"T\u00e2n Ch\u00e2u","type":"Th\u1ecb X\u00e3","location":"10 49 11N, 105 11 18E","provinceid":"89"}, {"districtid":"888","name":"Ph\u00fa T\u00e2n","type":"Huy\u1ec7n","location":"10 40 26N, 105 14 40E","provinceid":"89"}, {"districtid":"889","name":"Ch\u00e2u Ph\u00fa","type":"Huy\u1ec7n","location":"10 34 12N, 105 12 13E","provinceid":"89"}, {"districtid":"890","name":"T\u1ecbnh Bi\u00ean","type":"Huy\u1ec7n","location":"10 33 30N, 105 00 17E","provinceid":"89"}, {"districtid":"891","name":"Tri T\u00f4n","type":"Huy\u1ec7n","location":"10 24 41N, 104 56 58E","provinceid":"89"}, {"districtid":"892","name":"Ch\u00e2u Th\u00e0nh","type":"Huy\u1ec7n","location":"10 25 39N, 105 15 31E","provinceid":"89"}, {"districtid":"893","name":"Ch\u1ee3 M\u1edbi","type":"Huy\u1ec7n","location":"10 27 23N, 105 26 57E","provinceid":"89"}, {"districtid":"894","name":"Tho\u1ea1i S\u01a1n","type":"Huy\u1ec7n","location":"10 16 45N, 105 15 59E","provinceid":"89"}, {"districtid":"899","name":"R\u1ea1ch Gi\u00e1","type":"Th\u00e0nh Ph\u1ed1","location":"10 01 35N, 105 06 20E","provinceid":"91"}, {"districtid":"900","name":"H\u00e0 Ti\u00ean","type":"Th\u1ecb X\u00e3","location":"10 22 54N, 104 30 10E","provinceid":"91"}, {"districtid":"902","name":"Ki\u00ean L\u01b0\u01a1ng","type":"Huy\u1ec7n","location":"10 20 21N, 104 39 46E","provinceid":"91"}, {"districtid":"903","name":"H\u00f2n \u0110\u1ea5t","type":"Huy\u1ec7n","location":"10 14 20N, 104 55 57E","provinceid":"91"}, {"districtid":"904","name":"T\u00e2n Hi\u1ec7p","type":"Huy\u1ec7n","location":"10 05 18N, 105 14 04E","provinceid":"91"}, {"districtid":"905","name":"Ch\u00e2u Th\u00e0nh","type":"Huy\u1ec7n","location":"9 57 37N, 105 10 16E","provinceid":"91"}, {"districtid":"906","name":"Gi\u1ed3ng Gi\u1ec1ng","type":"Huy\u1ec7n","location":"9 56 05N, 105 22 06E","provinceid":"91"}, {"districtid":"907","name":"G\u00f2 Quao","type":"Huy\u1ec7n","location":"9 43 17N, 105 17 06E","provinceid":"91"}, {"districtid":"908","name":"An Bi\u00ean","type":"Huy\u1ec7n","location":"9 48 37N, 105 03 18E","provinceid":"91"}, {"districtid":"909","name":"An Minh","type":"Huy\u1ec7n","location":"9 40 24N, 104 59 05E","provinceid":"91"}, {"districtid":"910","name":"V\u0129nh Thu\u1eadn","type":"Huy\u1ec7n","location":"9 33 25N, 105 11 30E","provinceid":"91"}, {"districtid":"911","name":"Ph\u00fa Qu\u1ed1c","type":"Huy\u1ec7n","location":"10 13 44N, 103 57 25E","provinceid":"91"}, {"districtid":"912","name":"Ki\u00ean H\u1ea3i","type":"Huy\u1ec7n","location":"9 48 31N, 104 37 48E","provinceid":"91"}, {"districtid":"913","name":"U Minh Th\u01b0\u1ee3ng","type":"Huy\u1ec7n","location":"","provinceid":"91"}, {"districtid":"914","name":"Giang Th\u00e0nh","type":"Huy\u1ec7n","location":"","provinceid":"91"}, {"districtid":"916","name":"Ninh Ki\u1ec1u","type":"Qu\u1eadn","location":"10 01 58N, 105 45 34E","provinceid":"92"}, {"districtid":"917","name":"\u00d4 M\u00f4n","type":"Qu\u1eadn","location":"10 07 28N, 105 37 51E","provinceid":"92"}, {"districtid":"918","name":"B\u00ecnh Thu\u1ef7","type":"Qu\u1eadn","location":"10 03 42N, 105 43 17E","provinceid":"92"}, {"districtid":"919","name":"C\u00e1i R\u0103ng","type":"Qu\u1eadn","location":"9 59 57N, 105 46 56E","provinceid":"92"}, {"districtid":"923","name":"Th\u1ed1t N\u1ed1t","type":"Qu\u1eadn","location":"10 14 23N, 105 32 02E","provinceid":"92"}, {"districtid":"924","name":"V\u0129nh Th\u1ea1nh","type":"Huy\u1ec7n","location":"10 11 35N, 105 22 45E","provinceid":"92"}, {"districtid":"925","name":"C\u1edd \u0110\u1ecf","type":"Huy\u1ec7n","location":"10 02 48N, 105 29 46E","provinceid":"92"}, {"districtid":"926","name":"Phong \u0110i\u1ec1n","type":"Huy\u1ec7n","location":"9 59 57N, 105 39 35E","provinceid":"92"}, {"districtid":"927","name":"Th\u1edbi Lai","type":"Huy\u1ec7n","location":"","provinceid":"92"}, {"districtid":"930","name":"V\u1ecb Thanh","type":"Th\u1ecb X\u00e3","location":"9 45 15N, 105 24 50E","provinceid":"93"}, {"districtid":"931","name":"Ng\u00e3 B\u1ea3y","type":"Th\u1ecb X\u00e3","location":"","provinceid":"93"}, {"districtid":"932","name":"Ch\u00e2u Th\u00e0nh A","type":"Huy\u1ec7n","location":"9 55 50N, 105 38 31E","provinceid":"93"}, {"districtid":"933","name":"Ch\u00e2u Th\u00e0nh","type":"Huy\u1ec7n","location":"9 55 22N, 105 48 37E","provinceid":"93"}, {"districtid":"934","name":"Ph\u1ee5ng Hi\u1ec7p","type":"Huy\u1ec7n","location":"9 47 20N, 105 43 29E","provinceid":"93"}, {"districtid":"935","name":"V\u1ecb Thu\u1ef7","type":"Huy\u1ec7n","location":"9 48 05N, 105 32 13E","provinceid":"93"}, {"districtid":"936","name":"Long M\u1ef9","type":"Huy\u1ec7n","location":"9 40 47N, 105 30 53E","provinceid":"93"}, {"districtid":"941","name":"S\u00f3c Tr\u0103ng","type":"Th\u00e0nh Ph\u1ed1","location":"9 36 39N, 105 59 00E","provinceid":"94"}, {"districtid":"942","name":"Ch\u00e2u Th\u00e0nh","type":"Huy\u1ec7n","location":"","provinceid":"94"}, {"districtid":"943","name":"K\u1ebf S\u00e1ch","type":"Huy\u1ec7n","location":"9 49 30N, 105 57 25E","provinceid":"94"}, {"districtid":"944","name":"M\u1ef9 T\u00fa","type":"Huy\u1ec7n","location":"9 38 21N, 105 49 52E","provinceid":"94"}, {"districtid":"945","name":"C\u00f9 Lao Dung","type":"Huy\u1ec7n","location":"9 37 36N, 106 12 13E","provinceid":"94"}, {"districtid":"946","name":"Long Ph\u00fa","type":"Huy\u1ec7n","location":"9 34 38N, 106 06 07E","provinceid":"94"}, {"districtid":"947","name":"M\u1ef9 Xuy\u00ean","type":"Huy\u1ec7n","location":"9 28 16N, 105 55 51E","provinceid":"94"}, {"districtid":"948","name":"Ng\u00e3 N\u0103m","type":"Huy\u1ec7n","location":"9 31 38N, 105 37 22E","provinceid":"94"}, {"districtid":"949","name":"Th\u1ea1nh Tr\u1ecb","type":"Huy\u1ec7n","location":"9 28 05N, 105 43 02E","provinceid":"94"}, {"districtid":"950","name":"V\u0129nh Ch\u00e2u","type":"Huy\u1ec7n","location":"9 20 50N, 105 59 58E","provinceid":"94"}, {"districtid":"951","name":"Tr\u1ea7n \u0110\u1ec1","type":"Huy\u1ec7n","location":"","provinceid":"94"}, {"districtid":"954","name":"B\u1ea1c Li\u00eau","type":"Th\u1ecb X\u00e3","location":"9 16 05N, 105 45 08E","provinceid":"95"}, {"districtid":"956","name":"H\u1ed3ng D\u00e2n","type":"Huy\u1ec7n","location":"9 30 37N, 105 24 25E","provinceid":"95"}, {"districtid":"957","name":"Ph\u01b0\u1edbc Long","type":"Huy\u1ec7n","location":"9 23 13N, 105 24 41E","provinceid":"95"}, {"districtid":"958","name":"V\u0129nh L\u1ee3i","type":"Huy\u1ec7n","location":"9 16 51N, 105 40 54E","provinceid":"95"}, {"districtid":"959","name":"Gi\u00e1 Rai","type":"Huy\u1ec7n","location":"9 15 51N, 105 23 18E","provinceid":"95"}, {"districtid":"960","name":"\u0110\u00f4ng H\u1ea3i","type":"Huy\u1ec7n","location":"9 08 11N, 105 24 42E","provinceid":"95"}, {"districtid":"961","name":"Ho\u00e0 B\u00ecnh","type":"Huy\u1ec7n","location":"","provinceid":"95"}, {"districtid":"964","name":"C\u00e0 Mau","type":"Th\u00e0nh Ph\u1ed1","location":"9 10 33N, 105 11 11E","provinceid":"96"}, {"districtid":"966","name":"U Minh","type":"Huy\u1ec7n","location":"9 22 30N, 104 57 00E","provinceid":"96"}, {"districtid":"967","name":"Th\u1edbi B\u00ecnh","type":"Huy\u1ec7n","location":"9 22 50N, 105 07 35E","provinceid":"96"}, {"districtid":"968","name":"Tr\u1ea7n V\u0103n Th\u1eddi","type":"Huy\u1ec7n","location":"9 07 36N, 104 57 27E","provinceid":"96"}, {"districtid":"969","name":"C\u00e1i N\u01b0\u1edbc","type":"Huy\u1ec7n","location":"9 00 31N, 105 03 23E","provinceid":"96"}, {"districtid":"970","name":"\u0110\u1ea7m D\u01a1i","type":"Huy\u1ec7n","location":"8 57 48N, 105 13 56E","provinceid":"96"}, {"districtid":"971","name":"N\u0103m C\u0103n","type":"Huy\u1ec7n","location":"8 46 59N, 104 58 20E","provinceid":"96"}, {"districtid":"972","name":"Ph\u00fa T\u00e2n","type":"Huy\u1ec7n","location":"8 52 47N, 104 53 35E","provinceid":"96"}, {"districtid":"973","name":"Ng\u1ecdc Hi\u1ec3n","type":"Huy\u1ec7n","location":"8 40 47N, 104 57 58E","provinceid":"96"}]